[
  {
    "tokens": [
      "Δώσε",
      "το",
      "αντιβιοτικό"
    ],
    "tags": [
      "O",
      "O",
      "B-TYPE"
    ],
    "intent": "GIVE"
  },
  {
    "tokens": [
      "Παρέδωσε",
      "τη",
      "ιβουπροφένη",
      "μικρό",
      "από",
      "την",
      "ΜΕΘ"
    ],
    "tags": [
      "O",
      "O",
      "B-TYPE",
      "B-SIZE",
      "O",
      "O",
      "B-ZONE"
    ],
    "intent": "FETCH"
  },
  {
    "tokens": [
      "Βάλε",
      "αυτό",
      "εδώ"
    ],
    "tags": [
      "O",
      "O",
      "O"
    ],
    "intent": "PLACE"
  },
  {
    "tokens": [
      "Δώσε",
      "το",
      "μεγάλο"
    ],
    "tags": [
      "O",
      "O",
      "B-SIZE"
    ],
    "intent": "GIVE"
  },
  {
    "tokens": [
      "Πάρε",
      "τη",
      "οξύμετρο",
      "μεγάλη",
      "από",
      "την",
      "Φαρμακείο"
    ],
    "tags": [
      "O",
      "O",
      "B-TYPE",
      "B-SIZE",
      "O",
      "O",
      "B-ZONE"
    ],
    "intent": "FETCH"
  },
  {
    "tokens": [
      "Κλείσε",
      "το",
      "κουτί"
    ],
    "tags": [
      "O",
      "O",
      "B-TYPE"
    ],
    "intent": "CLOSE"
  },
  {
    "tokens": [
      "Τσέκαρε",
      "το",
      "σύριγγα"
    ],
    "tags": [
      "O",
      "O",
      "B-TYPE"
    ],
    "intent": "INSPECT"
  },
  {
    "tokens": [
      "Φέρτε",
      "τη",
      "επίδεσμο",
      "500mg",
      "από",
      "την",
      "Θάλαμος"
    ],
    "tags": [
      "O",
      "O",
      "B-TYPE",
      "B-SIZE",
      "O",
      "O",
      "B-ZONE"
    ],
    "intent": "FETCH"
  },
  {
    "tokens": [
      "Παρέδωσε",
      "τη",
      "αντιβιοτικό",
      "10x10",
      "από",
      "την",
      "Φαρμακείο"
    ],
    "tags": [
      "O",
      "O",
      "B-TYPE",
      "B-SIZE",
      "O",
      "O",
      "B-ZONE"
    ],
    "intent": "FETCH"
  },
  {
    "tokens": [
      "Δώσε",
      "το",
      "ιβουπροφένη"
    ],
    "tags": [
      "O",
      "O",
      "B-TYPE"
    ],
    "intent": "GIVE"
  },
  {
    "tokens": [
      "Φέρτε",
      "τη",
      "σφυγμόμετρο",
      "21g",
      "από",
      "την",
      "Αποθήκη"
    ],
    "tags": [
      "O",
      "O",
      "B-TYPE",
      "B-SIZE",
      "O",
      "O",
      "B-ZONE"
    ],
    "intent": "FETCH"
  },
  {
    "tokens": [
      "Τοποθέτησε",
      "το",
      "παρακεταμόλη",
      "αποστειρωμένο"
    ],
    "tags": [
      "O",
      "O",
      "B-TYPE",
      "B-STATE"
    ],
    "intent": "PLACE"
  },
  {
    "tokens": [
      "Ξεκλείδωσε",
      "το",
      "κουτί",
      "στη",
      "Αποθήκη"
    ],
    "tags": [
      "O",
      "O",
      "B-TYPE",
      "O",
      "B-ZONE"
    ],
    "intent": "OPEN"
  },
  {
    "tokens": [
      "Φέρτε",
      "τη",
      "γάζα",
      "18g",
      "από",
      "την",
      "Αποθήκη"
    ],
    "tags": [
      "O",
      "O",
      "B-TYPE",
      "B-SIZE",
      "O",
      "O",
      "B-ZONE"
    ],
    "intent": "FETCH"
  },
  {
    "tokens": [
      "Σύριγγα",
      "1ml"
    ],
    "tags": [
      "B-TYPE",
      "B-SIZE"
    ],
    "intent": "FETCH"
  },
  {
    "tokens": [
      "Φέρε",
      "τη",
      "σύριγγα",
      "10x10",
      "από",
      "την",
      "Αποθήκη"
    ],
    "tags": [
      "O",
      "O",
      "B-TYPE",
      "B-SIZE",
      "O",
      "O",
      "B-ZONE"
    ],
    "intent": "FETCH"
  },
  {
    "tokens": [
      "Κλείστο"
    ],
    "tags": [
      "O"
    ],
    "intent": "CLOSE"
  },
  {
    "tokens": [
      "Παρέδωσε",
      "τη",
      "βελόνα",
      "1ml",
      "από",
      "την",
      "Αποθήκη"
    ],
    "tags": [
      "O",
      "O",
      "B-TYPE",
      "B-SIZE",
      "O",
      "O",
      "B-ZONE"
    ],
    "intent": "FETCH"
  },
  {
    "tokens": [
      "Άφησε",
      "το",
      "θερμόμετρο",
      "ληγμένη"
    ],
    "tags": [
      "O",
      "O",
      "B-TYPE",
      "B-STATE"
    ],
    "intent": "PLACE"
  },
  {
    "tokens": [
      "Τσέκαρε",
      "το",
      "σύριγγα"
    ],
    "tags": [
      "O",
      "O",
      "B-TYPE"
    ],
    "intent": "INSPECT"
  },
  {
    "tokens": [
      "Παρέδωσε",
      "τη",
      "γάζες",
      "1ml",
      "από",
      "την",
      "ΜΕΘ"
    ],
    "tags": [
      "O",
      "O",
      "B-TYPE",
      "B-SIZE",
      "O",
      "O",
      "B-ZONE"
    ],
    "intent": "FETCH"
  },
  {
    "tokens": [
      "Ξεκλείδωσε",
      "το",
      "κουτί",
      "στη",
      "Θάλαμος"
    ],
    "tags": [
      "O",
      "O",
      "B-TYPE",
      "O",
      "B-ZONE"
    ],
    "intent": "OPEN"
  },
  {
    "tokens": [
      "Φέρε",
      "μου",
      "τη",
      "γάζα",
      "21g",
      "από",
      "την",
      "Φαρμακείο"
    ],
    "tags": [
      "O",
      "O",
      "O",
      "B-TYPE",
      "B-SIZE",
      "O",
      "O",
      "B-ZONE"
    ],
    "intent": "FETCH"
  },
  {
    "tokens": [
      "Κλείσε",
      "το",
      "κουτί"
    ],
    "tags": [
      "O",
      "O",
      "B-TYPE"
    ],
    "intent": "CLOSE"
  },
  {
    "tokens": [
      "Δες",
      "το",
      "κουτί"
    ],
    "tags": [
      "O",
      "O",
      "B-TYPE"
    ],
    "intent": "INSPECT"
  },
  {
    "tokens": [
      "Άφησε",
      "το",
      "σφυγμόμετρο",
      "ληγμένη"
    ],
    "tags": [
      "O",
      "O",
      "B-TYPE",
      "B-STATE"
    ],
    "intent": "PLACE"
  },
  {
    "tokens": [
      "Τοποθέτησε",
      "το",
      "βελόνα",
      "ληγμένο"
    ],
    "tags": [
      "O",
      "O",
      "B-TYPE",
      "B-STATE"
    ],
    "intent": "PLACE"
  },
  {
    "tokens": [
      "Δώσε",
      "το",
      "γάζα"
    ],
    "tags": [
      "O",
      "O",
      "B-TYPE"
    ],
    "intent": "GIVE"
  },
  {
    "tokens": [
      "Φέρτε",
      "τη",
      "σύριγγα",
      "5x5",
      "από",
      "την",
      "ΜΕΘ"
    ],
    "tags": [
      "O",
      "O",
      "B-TYPE",
      "B-SIZE",
      "O",
      "O",
      "B-ZONE"
    ],
    "intent": "FETCH"
  },
  {
    "tokens": [
      "Τοποθέτησε",
      "το",
      "επίδεσμος",
      "ανοιχτή"
    ],
    "tags": [
      "O",
      "O",
      "B-TYPE",
      "B-STATE"
    ],
    "intent": "PLACE"
  },
  {
    "tokens": [
      "Άνοιξε",
      "το"
    ],
    "tags": [
      "O",
      "O"
    ],
    "intent": "OPEN"
  },
  {
    "tokens": [
      "Κλείσε",
      "το",
      "κουτί"
    ],
    "tags": [
      "O",
      "O",
      "B-TYPE"
    ],
    "intent": "CLOSE"
  },
  {
    "tokens": [
      "Τοποθέτησε",
      "το",
      "θερμόμετρο",
      "ανοιχτό"
    ],
    "tags": [
      "O",
      "O",
      "B-TYPE",
      "B-STATE"
    ],
    "intent": "PLACE"
  },
  {
    "tokens": [
      "Φέρτε",
      "τη",
      "θερμόμετρο",
      "5ml",
      "από",
      "την",
      "Θάλαμος"
    ],
    "tags": [
      "O",
      "O",
      "B-TYPE",
      "B-SIZE",
      "O",
      "O",
      "B-ZONE"
    ],
    "intent": "FETCH"
  },
  {
    "tokens": [
      "Άνοιξε",
      "το",
      "κουτί",
      "στη",
      "Φαρμακείο"
    ],
    "tags": [
      "O",
      "O",
      "B-TYPE",
      "O",
      "B-ZONE"
    ],
    "intent": "OPEN"
  },
  {
    "tokens": [
      "Χορήγησε",
      "το",
      "γάζα"
    ],
    "tags": [
      "O",
      "O",
      "B-TYPE"
    ],
    "intent": "GIVE"
  },
  {
    "tokens": [
      "Κλείσε",
      "το",
      "κουτί"
    ],
    "tags": [
      "O",
      "O",
      "B-TYPE"
    ],
    "intent": "CLOSE"
  },
  {
    "tokens": [
      "Κλείστο"
    ],
    "tags": [
      "O"
    ],
    "intent": "CLOSE"
  },
  {
    "tokens": [
      "Παρέδωσε",
      "τη",
      "παρακεταμόλη",
      "μεγάλο",
      "από",
      "την",
      "Αποθήκη"
    ],
    "tags": [
      "O",
      "O",
      "B-TYPE",
      "B-SIZE",
      "O",
      "O",
      "B-ZONE"
    ],
    "intent": "FETCH"
  },
  {
    "tokens": [
      "Εξέτασε",
      "το",
      "ιβουπροφένη"
    ],
    "tags": [
      "O",
      "O",
      "B-TYPE"
    ],
    "intent": "INSPECT"
  },
  {
    "tokens": [
      "Χορήγησε",
      "το",
      "ιβουπροφένη"
    ],
    "tags": [
      "O",
      "O",
      "B-TYPE"
    ],
    "intent": "GIVE"
  },
  {
    "tokens": [
      "Φέρε",
      "τη",
      "ιβουπροφένη",
      "5x5",
      "από",
      "την",
      "Φαρμακείο"
    ],
    "tags": [
      "O",
      "O",
      "B-TYPE",
      "B-SIZE",
      "O",
      "O",
      "B-ZONE"
    ],
    "intent": "FETCH"
  },
  {
    "tokens": [
      "Φέρε",
      "μου",
      "τη",
      "γάζες",
      "21g",
      "από",
      "την",
      "ΜΕΘ"
    ],
    "tags": [
      "O",
      "O",
      "O",
      "B-TYPE",
      "B-SIZE",
      "O",
      "O",
      "B-ZONE"
    ],
    "intent": "FETCH"
  },
  {
    "tokens": [
      "Άνοιξε",
      "το",
      "κουτί",
      "στη",
      "Φαρμακείο"
    ],
    "tags": [
      "O",
      "O",
      "B-TYPE",
      "O",
      "B-ZONE"
    ],
    "intent": "OPEN"
  },
  {
    "tokens": [
      "Παρέδωσε",
      "τη",
      "οξύμετρο",
      "μεγάλη",
      "από",
      "την",
      "ΜΕΘ"
    ],
    "tags": [
      "O",
      "O",
      "B-TYPE",
      "B-SIZE",
      "O",
      "O",
      "B-ZONE"
    ],
    "intent": "FETCH"
  },
  {
    "tokens": [
      "Δώσε",
      "το",
      "γάζα"
    ],
    "tags": [
      "O",
      "O",
      "B-TYPE"
    ],
    "intent": "GIVE"
  },
  {
    "tokens": [
      "Ληγμένο",
      "είναι;"
    ],
    "tags": [
      "B-STATE",
      "O"
    ],
    "intent": "INSPECT"
  },
  {
    "tokens": [
      "Κλείσε",
      "το",
      "κουτί"
    ],
    "tags": [
      "O",
      "O",
      "B-TYPE"
    ],
    "intent": "CLOSE"
  },
  {
    "tokens": [
      "Φέρτε",
      "τη",
      "επίδεσμο",
      "μεγάλο",
      "από",
      "την",
      "Φαρμακείο"
    ],
    "tags": [
      "O",
      "O",
      "B-TYPE",
      "B-SIZE",
      "O",
      "O",
      "B-ZONE"
    ],
    "intent": "FETCH"
  },
  {
    "tokens": [
      "Αποθήκη",
      "γάζες"
    ],
    "tags": [
      "B-ZONE",
      "B-TYPE"
    ],
    "intent": "FETCH"
  },
  {
    "tokens": [
      "Άνοιξε",
      "το",
      "κουτί",
      "στη",
      "Φαρμακείο"
    ],
    "tags": [
      "O",
      "O",
      "B-TYPE",
      "O",
      "B-ZONE"
    ],
    "intent": "OPEN"
  },
  {
    "tokens": [
      "Βελόνα",
      "21g"
    ],
    "tags": [
      "B-TYPE",
      "B-SIZE"
    ],
    "intent": "FETCH"
  },
  {
    "tokens": [
      "Φέρε",
      "μου",
      "τη",
      "παρακεταμόλη",
      "5x5",
      "από",
      "την",
      "Αποθήκη"
    ],
    "tags": [
      "O",
      "O",
      "O",
      "B-TYPE",
      "B-SIZE",
      "O",
      "O",
      "B-ZONE"
    ],
    "intent": "FETCH"
  },
  {
    "tokens": [
      "Κλείστο"
    ],
    "tags": [
      "O"
    ],
    "intent": "CLOSE"
  },
  {
    "tokens": [
      "Εξέτασε",
      "το",
      "αντιβιοτικό"
    ],
    "tags": [
      "O",
      "O",
      "B-TYPE"
    ],
    "intent": "INSPECT"
  },
  {
    "tokens": [
      "Άφησε",
      "το",
      "θερμόμετρο",
      "ανοιχτό"
    ],
    "tags": [
      "O",
      "O",
      "B-TYPE",
      "B-STATE"
    ],
    "intent": "PLACE"
  },
  {
    "tokens": [
      "Ξεκλείδωσε",
      "το",
      "κουτί",
      "στη",
      "Αποθήκη"
    ],
    "tags": [
      "O",
      "O",
      "B-TYPE",
      "O",
      "B-ZONE"
    ],
    "intent": "OPEN"
  },
  {
    "tokens": [
      "Άφησε",
      "το",
      "γάζες",
      "ληγμένη"
    ],
    "tags": [
      "O",
      "O",
      "B-TYPE",
      "B-STATE"
    ],
    "intent": "PLACE"
  },
  {
    "tokens": [
      "Ξεκλείδωσε",
      "το",
      "κουτί",
      "στη",
      "ΜΕΘ"
    ],
    "tags": [
      "O",
      "O",
      "B-TYPE",
      "O",
      "B-ZONE"
    ],
    "intent": "OPEN"
  },
  {
    "tokens": [
      "Τσέκαρε",
      "το",
      "ιβουπροφένη"
    ],
    "tags": [
      "O",
      "O",
      "B-TYPE"
    ],
    "intent": "INSPECT"
  },
  {
    "tokens": [
      "Τοποθέτησε",
      "το",
      "οξύμετρο",
      "ανοιχτό"
    ],
    "tags": [
      "O",
      "O",
      "B-TYPE",
      "B-STATE"
    ],
    "intent": "PLACE"
  },
  {
    "tokens": [
      "Φέρε",
      "τη",
      "κουτί",
      "μεγάλη",
      "από",
      "την",
      "ΜΕΘ"
    ],
    "tags": [
      "O",
      "O",
      "B-TYPE",
      "B-SIZE",
      "O",
      "O",
      "B-ZONE"
    ],
    "intent": "FETCH"
  },
  {
    "tokens": [
      "Φέρτε",
      "τη",
      "σύριγγα",
      "5ml",
      "από",
      "την",
      "Θάλαμος"
    ],
    "tags": [
      "O",
      "O",
      "B-TYPE",
      "B-SIZE",
      "O",
      "O",
      "B-ZONE"
    ],
    "intent": "FETCH"
  },
  {
    "tokens": [
      "Χορήγησε",
      "το",
      "ιβουπροφένη"
    ],
    "tags": [
      "O",
      "O",
      "B-TYPE"
    ],
    "intent": "GIVE"
  },
  {
    "tokens": [
      "Κλείσε",
      "το",
      "κουτί"
    ],
    "tags": [
      "O",
      "O",
      "B-TYPE"
    ],
    "intent": "CLOSE"
  },
  {
    "tokens": [
      "Χορήγησε",
      "το",
      "αντιβιοτικό"
    ],
    "tags": [
      "O",
      "O",
      "B-TYPE"
    ],
    "intent": "GIVE"
  },
  {
    "tokens": [
      "Τοποθέτησε",
      "το",
      "γάζες",
      "ανοιχτή"
    ],
    "tags": [
      "O",
      "O",
      "B-TYPE",
      "B-STATE"
    ],
    "intent": "PLACE"
  },
  {
    "tokens": [
      "Αποθήκη",
      "γάζες"
    ],
    "tags": [
      "B-ZONE",
      "B-TYPE"
    ],
    "intent": "FETCH"
  },
  {
    "tokens": [
      "Κλείσε",
      "το",
      "κουτί"
    ],
    "tags": [
      "O",
      "O",
      "B-TYPE"
    ],
    "intent": "CLOSE"
  },
  {
    "tokens": [
      "Παρέδωσε",
      "τη",
      "παρακεταμόλη",
      "1ml",
      "από",
      "την",
      "Θάλαμος"
    ],
    "tags": [
      "O",
      "O",
      "B-TYPE",
      "B-SIZE",
      "O",
      "O",
      "B-ZONE"
    ],
    "intent": "FETCH"
  },
  {
    "tokens": [
      "Παρέδωσε",
      "τη",
      "βελόνα",
      "21g",
      "από",
      "την",
      "Αποθήκη"
    ],
    "tags": [
      "O",
      "O",
      "B-TYPE",
      "B-SIZE",
      "O",
      "O",
      "B-ZONE"
    ],
    "intent": "FETCH"
  },
  {
    "tokens": [
      "Παρακεταμόλη",
      "ΜΕΘ"
    ],
    "tags": [
      "B-TYPE",
      "B-ZONE"
    ],
    "intent": "FETCH"
  },
  {
    "tokens": [
      "Έλεγξε",
      "το",
      "επίδεσμο"
    ],
    "tags": [
      "O",
      "O",
      "B-TYPE"
    ],
    "intent": "INSPECT"
  },
  {
    "tokens": [
      "Φέρε",
      "τη",
      "γάζα",
      "5ml",
      "από",
      "την",
      "Αποθήκη"
    ],
    "tags": [
      "O",
      "O",
      "B-TYPE",
      "B-SIZE",
      "O",
      "O",
      "B-ZONE"
    ],
    "intent": "FETCH"
  },
  {
    "tokens": [
      "Ληγμένο",
      "είναι;"
    ],
    "tags": [
      "B-STATE",
      "O"
    ],
    "intent": "INSPECT"
  },
  {
    "tokens": [
      "Παρέδωσε",
      "τη",
      "γάζα",
      "18g",
      "από",
      "την",
      "ΜΕΘ"
    ],
    "tags": [
      "O",
      "O",
      "B-TYPE",
      "B-SIZE",
      "O",
      "O",
      "B-ZONE"
    ],
    "intent": "FETCH"
  },
  {
    "tokens": [
      "Χορήγησε",
      "το",
      "ιβουπροφένη"
    ],
    "tags": [
      "O",
      "O",
      "B-TYPE"
    ],
    "intent": "GIVE"
  },
  {
    "tokens": [
      "Δώσε",
      "το",
      "αντιβιοτικό"
    ],
    "tags": [
      "O",
      "O",
      "B-TYPE"
    ],
    "intent": "GIVE"
  },
  {
    "tokens": [
      "Φέρε",
      "μου",
      "τη",
      "παρακεταμόλη",
      "5ml",
      "από",
      "την",
      "ΜΕΘ"
    ],
    "tags": [
      "O",
      "O",
      "O",
      "B-TYPE",
      "B-SIZE",
      "O",
      "O",
      "B-ZONE"
    ],
    "intent": "FETCH"
  },
  {
    "tokens": [
      "Τοποθέτησε",
      "το",
      "σύριγγα",
      "ανοιχτή"
    ],
    "tags": [
      "O",
      "O",
      "B-TYPE",
      "B-STATE"
    ],
    "intent": "PLACE"
  },
  {
    "tokens": [
      "Τοποθέτησε",
      "το",
      "γάζες",
      "ληγμένο"
    ],
    "tags": [
      "O",
      "O",
      "B-TYPE",
      "B-STATE"
    ],
    "intent": "PLACE"
  },
  {
    "tokens": [
      "Παρέδωσε",
      "τη",
      "γάζες",
      "μικρή",
      "από",
      "την",
      "Αποθήκη"
    ],
    "tags": [
      "O",
      "O",
      "B-TYPE",
      "B-SIZE",
      "O",
      "O",
      "B-ZONE"
    ],
    "intent": "FETCH"
  },
  {
    "tokens": [
      "Άφησε",
      "το",
      "ιβουπροφένη",
      "αποστειρωμένη"
    ],
    "tags": [
      "O",
      "O",
      "B-TYPE",
      "B-STATE"
    ],
    "intent": "PLACE"
  },
  {
    "tokens": [
      "Φέρε",
      "τη",
      "θερμόμετρο",
      "μικρό",
      "από",
      "την",
      "Θάλαμος"
    ],
    "tags": [
      "O",
      "O",
      "B-TYPE",
      "B-SIZE",
      "O",
      "O",
      "B-ZONE"
    ],
    "intent": "FETCH"
  },
  {
    "tokens": [
      "Έλεγξε",
      "τα",
      "ληγμένα"
    ],
    "tags": [
      "O",
      "O",
      "B-STATE"
    ],
    "intent": "INSPECT"
  },
  {
    "tokens": [
      "Τοποθέτησε",
      "το",
      "γάζα",
      "ανοιχτή"
    ],
    "tags": [
      "O",
      "O",
      "B-TYPE",
      "B-STATE"
    ],
    "intent": "PLACE"
  },
  {
    "tokens": [
      "Άνοιξε",
      "το"
    ],
    "tags": [
      "O",
      "O"
    ],
    "intent": "OPEN"
  },
  {
    "tokens": [
      "Τοποθέτησε",
      "το",
      "παρακεταμόλη",
      "ληγμένη"
    ],
    "tags": [
      "O",
      "O",
      "B-TYPE",
      "B-STATE"
    ],
    "intent": "PLACE"
  },
  {
    "tokens": [
      "Δώσε",
      "το",
      "γάζα"
    ],
    "tags": [
      "O",
      "O",
      "B-TYPE"
    ],
    "intent": "GIVE"
  },
  {
    "tokens": [
      "Ξεκλείδωσε",
      "το",
      "κουτί",
      "στη",
      "Φαρμακείο"
    ],
    "tags": [
      "O",
      "O",
      "B-TYPE",
      "O",
      "B-ZONE"
    ],
    "intent": "OPEN"
  },
  {
    "tokens": [
      "Τη",
      "μεγάλη",
      "γάζα"
    ],
    "tags": [
      "O",
      "B-SIZE",
      "B-TYPE"
    ],
    "intent": "FETCH"
  },
  {
    "tokens": [
      "Τσέκαρε",
      "το",
      "ιβουπροφένη"
    ],
    "tags": [
      "O",
      "O",
      "B-TYPE"
    ],
    "intent": "INSPECT"
  },
  {
    "tokens": [
      "Άφησε",
      "το",
      "επίδεσμο",
      "ανοιχτή"
    ],
    "tags": [
      "O",
      "O",
      "B-TYPE",
      "B-STATE"
    ],
    "intent": "PLACE"
  },
  {
    "tokens": [
      "Φέρε",
      "μου",
      "τη",
      "σφυγμόμετρο",
      "5ml",
      "από",
      "την",
      "Θάλαμος"
    ],
    "tags": [
      "O",
      "O",
      "O",
      "B-TYPE",
      "B-SIZE",
      "O",
      "O",
      "B-ZONE"
    ],
    "intent": "FETCH"
  },
  {
    "tokens": [
      "Πάρε",
      "τη",
      "γάζα",
      "μικρή",
      "από",
      "την",
      "Φαρμακείο"
    ],
    "tags": [
      "O",
      "O",
      "B-TYPE",
      "B-SIZE",
      "O",
      "O",
      "B-ZONE"
    ],
    "intent": "FETCH"
  },
  {
    "tokens": [
      "Βάλε",
      "αυτό",
      "εδώ"
    ],
    "tags": [
      "O",
      "O",
      "O"
    ],
    "intent": "PLACE"
  },
  {
    "tokens": [
      "Εξέτασε",
      "το",
      "οξύμετρο"
    ],
    "tags": [
      "O",
      "O",
      "B-TYPE"
    ],
    "intent": "INSPECT"
  },
  {
    "tokens": [
      "Άνοιξε",
      "το",
      "κουτί",
      "στη",
      "ΜΕΘ"
    ],
    "tags": [
      "O",
      "O",
      "B-TYPE",
      "O",
      "B-ZONE"
    ],
    "intent": "OPEN"
  },
  {
    "tokens": [
      "Άφησε",
      "το",
      "κουτί",
      "αποστειρωμένη"
    ],
    "tags": [
      "O",
      "O",
      "B-TYPE",
      "B-STATE"
    ],
    "intent": "PLACE"
  },
  {
    "tokens": [
      "Ξεκλείδωσε",
      "το",
      "κουτί",
      "στη",
      "Αποθήκη"
    ],
    "tags": [
      "O",
      "O",
      "B-TYPE",
      "O",
      "B-ZONE"
    ],
    "intent": "OPEN"
  },
  {
    "tokens": [
      "Ληγμένο",
      "είναι;"
    ],
    "tags": [
      "B-STATE",
      "O"
    ],
    "intent": "INSPECT"
  },
  {
    "tokens": [
      "Κλείστο"
    ],
    "tags": [
      "O"
    ],
    "intent": "CLOSE"
  },
  {
    "tokens": [
      "Παρέδωσε",
      "τη",
      "οξύμετρο",
      "1ml",
      "από",
      "την",
      "Αποθήκη"
    ],
    "tags": [
      "O",
      "O",
      "B-TYPE",
      "B-SIZE",
      "O",
      "O",
      "B-ZONE"
    ],
    "intent": "FETCH"
  },
  {
    "tokens": [
      "Έλεγξε",
      "τα",
      "ληγμένα"
    ],
    "tags": [
      "O",
      "O",
      "B-STATE"
    ],
    "intent": "INSPECT"
  },
  {
    "tokens": [
      "Άφησε",
      "το",
      "παρακεταμόλη",
      "ανοιχτή"
    ],
    "tags": [
      "O",
      "O",
      "B-TYPE",
      "B-STATE"
    ],
    "intent": "PLACE"
  },
  {
    "tokens": [
      "Κλείσε",
      "το",
      "κουτί"
    ],
    "tags": [
      "O",
      "O",
      "B-TYPE"
    ],
    "intent": "CLOSE"
  },
  {
    "tokens": [
      "Κλείσε",
      "το",
      "κουτί"
    ],
    "tags": [
      "O",
      "O",
      "B-TYPE"
    ],
    "intent": "CLOSE"
  },
  {
    "tokens": [
      "Αποθήκη",
      "γάζες"
    ],
    "tags": [
      "B-ZONE",
      "B-TYPE"
    ],
    "intent": "FETCH"
  },
  {
    "tokens": [
      "Ξεκλείδωσε",
      "το",
      "κουτί",
      "στη",
      "Φαρμακείο"
    ],
    "tags": [
      "O",
      "O",
      "B-TYPE",
      "O",
      "B-ZONE"
    ],
    "intent": "OPEN"
  },
  {
    "tokens": [
      "Τοποθέτησε",
      "το",
      "επίδεσμος",
      "ανοιχτό"
    ],
    "tags": [
      "O",
      "O",
      "B-TYPE",
      "B-STATE"
    ],
    "intent": "PLACE"
  },
  {
    "tokens": [
      "Άνοιξε",
      "το",
      "κουτί",
      "στη",
      "Αποθήκη"
    ],
    "tags": [
      "O",
      "O",
      "B-TYPE",
      "O",
      "B-ZONE"
    ],
    "intent": "OPEN"
  },
  {
    "tokens": [
      "Φέρε",
      "τη",
      "κουτί",
      "5ml",
      "από",
      "την",
      "Θάλαμος"
    ],
    "tags": [
      "O",
      "O",
      "B-TYPE",
      "B-SIZE",
      "O",
      "O",
      "B-ZONE"
    ],
    "intent": "FETCH"
  },
  {
    "tokens": [
      "Δες",
      "το",
      "οξύμετρο"
    ],
    "tags": [
      "O",
      "O",
      "B-TYPE"
    ],
    "intent": "INSPECT"
  },
  {
    "tokens": [
      "Άφησε",
      "το",
      "παρακεταμόλη",
      "ανοιχτή"
    ],
    "tags": [
      "O",
      "O",
      "B-TYPE",
      "B-STATE"
    ],
    "intent": "PLACE"
  },
  {
    "tokens": [
      "Πάρε",
      "τη",
      "γάζες",
      "18g",
      "από",
      "την",
      "ΜΕΘ"
    ],
    "tags": [
      "O",
      "O",
      "B-TYPE",
      "B-SIZE",
      "O",
      "O",
      "B-ZONE"
    ],
    "intent": "FETCH"
  },
  {
    "tokens": [
      "Δώσε",
      "το",
      "αντιβιοτικό"
    ],
    "tags": [
      "O",
      "O",
      "B-TYPE"
    ],
    "intent": "GIVE"
  },
  {
    "tokens": [
      "Έλεγξε",
      "το",
      "ιβουπροφένη"
    ],
    "tags": [
      "O",
      "O",
      "B-TYPE"
    ],
    "intent": "INSPECT"
  },
  {
    "tokens": [
      "Έλεγξε",
      "τα",
      "ληγμένα"
    ],
    "tags": [
      "O",
      "O",
      "B-STATE"
    ],
    "intent": "INSPECT"
  },
  {
    "tokens": [
      "Φέρε",
      "μου",
      "τη",
      "αντιβιοτικό",
      "21g",
      "από",
      "την",
      "Φαρμακείο"
    ],
    "tags": [
      "O",
      "O",
      "O",
      "B-TYPE",
      "B-SIZE",
      "O",
      "O",
      "B-ZONE"
    ],
    "intent": "FETCH"
  },
  {
    "tokens": [
      "Χορήγησε",
      "το",
      "γάζα"
    ],
    "tags": [
      "O",
      "O",
      "B-TYPE"
    ],
    "intent": "GIVE"
  },
  {
    "tokens": [
      "Αποθήκη",
      "γάζες"
    ],
    "tags": [
      "B-ZONE",
      "B-TYPE"
    ],
    "intent": "FETCH"
  },
  {
    "tokens": [
      "Παρέδωσε",
      "τη",
      "σφυγμόμετρο",
      "μεσαίο",
      "από",
      "την",
      "Αποθήκη"
    ],
    "tags": [
      "O",
      "O",
      "B-TYPE",
      "B-SIZE",
      "O",
      "O",
      "B-ZONE"
    ],
    "intent": "FETCH"
  },
  {
    "tokens": [
      "Βάλε",
      "το",
      "βελόνα",
      "αποστειρωμένη"
    ],
    "tags": [
      "O",
      "O",
      "B-TYPE",
      "B-STATE"
    ],
    "intent": "PLACE"
  },
  {
    "tokens": [
      "Παρακεταμόλη",
      "ΜΕΘ"
    ],
    "tags": [
      "B-TYPE",
      "B-ZONE"
    ],
    "intent": "FETCH"
  },
  {
    "tokens": [
      "Φέρτε",
      "τη",
      "γάζες",
      "10ml",
      "από",
      "την",
      "Θάλαμος"
    ],
    "tags": [
      "O",
      "O",
      "B-TYPE",
      "B-SIZE",
      "O",
      "O",
      "B-ZONE"
    ],
    "intent": "FETCH"
  },
  {
    "tokens": [
      "Ξεκλείδωσε",
      "το",
      "κουτί",
      "στη",
      "Αποθήκη"
    ],
    "tags": [
      "O",
      "O",
      "B-TYPE",
      "O",
      "B-ZONE"
    ],
    "intent": "OPEN"
  },
  {
    "tokens": [
      "Πάρε",
      "τη",
      "επίδεσμο",
      "μικρό",
      "από",
      "την",
      "Θάλαμος"
    ],
    "tags": [
      "O",
      "O",
      "B-TYPE",
      "B-SIZE",
      "O",
      "O",
      "B-ZONE"
    ],
    "intent": "FETCH"
  },
  {
    "tokens": [
      "Κλείστο"
    ],
    "tags": [
      "O"
    ],
    "intent": "CLOSE"
  },
  {
    "tokens": [
      "Άνοιξε",
      "το",
      "κουτί",
      "στη",
      "Αποθήκη"
    ],
    "tags": [
      "O",
      "O",
      "B-TYPE",
      "O",
      "B-ZONE"
    ],
    "intent": "OPEN"
  },
  {
    "tokens": [
      "Φέρε",
      "τη",
      "βελόνα",
      "μεγάλο",
      "από",
      "την",
      "ΜΕΘ"
    ],
    "tags": [
      "O",
      "O",
      "B-TYPE",
      "B-SIZE",
      "O",
      "O",
      "B-ZONE"
    ],
    "intent": "FETCH"
  },
  {
    "tokens": [
      "Τη",
      "μεγάλη",
      "γάζα"
    ],
    "tags": [
      "O",
      "B-SIZE",
      "B-TYPE"
    ],
    "intent": "FETCH"
  },
  {
    "tokens": [
      "Παρακεταμόλη",
      "ΜΕΘ"
    ],
    "tags": [
      "B-TYPE",
      "B-ZONE"
    ],
    "intent": "FETCH"
  },
  {
    "tokens": [
      "Δώσε",
      "το",
      "μεγάλο"
    ],
    "tags": [
      "O",
      "O",
      "B-SIZE"
    ],
    "intent": "GIVE"
  },
  {
    "tokens": [
      "Φέρε",
      "τη",
      "κουτί",
      "18g",
      "από",
      "την",
      "Αποθήκη"
    ],
    "tags": [
      "O",
      "O",
      "B-TYPE",
      "B-SIZE",
      "O",
      "O",
      "B-ZONE"
    ],
    "intent": "FETCH"
  },
  {
    "tokens": [
      "Βάλε",
      "το",
      "κουτί",
      "ληγμένο"
    ],
    "tags": [
      "O",
      "O",
      "B-TYPE",
      "B-STATE"
    ],
    "intent": "PLACE"
  },
  {
    "tokens": [
      "Φέρε",
      "μου",
      "τη",
      "γάζα",
      "μεγάλο",
      "από",
      "την",
      "Αποθήκη"
    ],
    "tags": [
      "O",
      "O",
      "O",
      "B-TYPE",
      "B-SIZE",
      "O",
      "O",
      "B-ZONE"
    ],
    "intent": "FETCH"
  },
  {
    "tokens": [
      "Τοποθέτησε",
      "το",
      "γάζες",
      "ανοιχτή"
    ],
    "tags": [
      "O",
      "O",
      "B-TYPE",
      "B-STATE"
    ],
    "intent": "PLACE"
  },
  {
    "tokens": [
      "Κλείσε",
      "το",
      "κουτί"
    ],
    "tags": [
      "O",
      "O",
      "B-TYPE"
    ],
    "intent": "CLOSE"
  },
  {
    "tokens": [
      "Χορήγησε",
      "το",
      "αντιβιοτικό"
    ],
    "tags": [
      "O",
      "O",
      "B-TYPE"
    ],
    "intent": "GIVE"
  },
  {
    "tokens": [
      "Έλεγξε",
      "το",
      "επίδεσμο"
    ],
    "tags": [
      "O",
      "O",
      "B-TYPE"
    ],
    "intent": "INSPECT"
  },
  {
    "tokens": [
      "Χορήγησε",
      "το",
      "αντιβιοτικό"
    ],
    "tags": [
      "O",
      "O",
      "B-TYPE"
    ],
    "intent": "GIVE"
  },
  {
    "tokens": [
      "Παρέδωσε",
      "τη",
      "επίδεσμος",
      "μεγάλη",
      "από",
      "την",
      "ΜΕΘ"
    ],
    "tags": [
      "O",
      "O",
      "B-TYPE",
      "B-SIZE",
      "O",
      "O",
      "B-ZONE"
    ],
    "intent": "FETCH"
  },
  {
    "tokens": [
      "Δώσε",
      "εκείνο"
    ],
    "tags": [
      "O",
      "O"
    ],
    "intent": "GIVE"
  },
  {
    "tokens": [
      "Εξέτασε",
      "το",
      "παρακεταμόλη"
    ],
    "tags": [
      "O",
      "O",
      "B-TYPE"
    ],
    "intent": "INSPECT"
  },
  {
    "tokens": [
      "Τσέκαρε",
      "το",
      "ιβουπροφένη"
    ],
    "tags": [
      "O",
      "O",
      "B-TYPE"
    ],
    "intent": "INSPECT"
  },
  {
    "tokens": [
      "Φέρε",
      "μου",
      "τη",
      "σφυγμόμετρο",
      "5ml",
      "από",
      "την",
      "Θάλαμος"
    ],
    "tags": [
      "O",
      "O",
      "O",
      "B-TYPE",
      "B-SIZE",
      "O",
      "O",
      "B-ZONE"
    ],
    "intent": "FETCH"
  },
  {
    "tokens": [
      "Κλείστο"
    ],
    "tags": [
      "O"
    ],
    "intent": "CLOSE"
  },
  {
    "tokens": [
      "Φέρε",
      "τη",
      "βελόνα",
      "21g",
      "από",
      "την",
      "ΜΕΘ"
    ],
    "tags": [
      "O",
      "O",
      "B-TYPE",
      "B-SIZE",
      "O",
      "O",
      "B-ZONE"
    ],
    "intent": "FETCH"
  },
  {
    "tokens": [
      "Πάρε",
      "τη",
      "σφυγμόμετρο",
      "μεσαίο",
      "από",
      "την",
      "Αποθήκη"
    ],
    "tags": [
      "O",
      "O",
      "B-TYPE",
      "B-SIZE",
      "O",
      "O",
      "B-ZONE"
    ],
    "intent": "FETCH"
  },
  {
    "tokens": [
      "Κλείσε",
      "το",
      "κουτί"
    ],
    "tags": [
      "O",
      "O",
      "B-TYPE"
    ],
    "intent": "CLOSE"
  },
  {
    "tokens": [
      "Φέρε",
      "μου",
      "τη",
      "σφυγμόμετρο",
      "1ml",
      "από",
      "την",
      "ΜΕΘ"
    ],
    "tags": [
      "O",
      "O",
      "O",
      "B-TYPE",
      "B-SIZE",
      "O",
      "O",
      "B-ZONE"
    ],
    "intent": "FETCH"
  },
  {
    "tokens": [
      "Τοποθέτησε",
      "το",
      "γάζα",
      "ανοιχτή"
    ],
    "tags": [
      "O",
      "O",
      "B-TYPE",
      "B-STATE"
    ],
    "intent": "PLACE"
  },
  {
    "tokens": [
      "Χορήγησε",
      "το",
      "αντιβιοτικό"
    ],
    "tags": [
      "O",
      "O",
      "B-TYPE"
    ],
    "intent": "GIVE"
  },
  {
    "tokens": [
      "Άνοιξε",
      "το",
      "κουτί",
      "στη",
      "ΜΕΘ"
    ],
    "tags": [
      "O",
      "O",
      "B-TYPE",
      "O",
      "B-ZONE"
    ],
    "intent": "OPEN"
  },
  {
    "tokens": [
      "Δώσε",
      "το",
      "ιβουπροφένη"
    ],
    "tags": [
      "O",
      "O",
      "B-TYPE"
    ],
    "intent": "GIVE"
  },
  {
    "tokens": [
      "Τσέκαρε",
      "το",
      "σφυγμόμετρο"
    ],
    "tags": [
      "O",
      "O",
      "B-TYPE"
    ],
    "intent": "INSPECT"
  },
  {
    "tokens": [
      "Άφησε",
      "το",
      "θερμόμετρο",
      "ληγμένη"
    ],
    "tags": [
      "O",
      "O",
      "B-TYPE",
      "B-STATE"
    ],
    "intent": "PLACE"
  },
  {
    "tokens": [
      "Κλείσε",
      "το",
      "κουτί"
    ],
    "tags": [
      "O",
      "O",
      "B-TYPE"
    ],
    "intent": "CLOSE"
  },
  {
    "tokens": [
      "Έλεγξε",
      "το",
      "επίδεσμος"
    ],
    "tags": [
      "O",
      "O",
      "B-TYPE"
    ],
    "intent": "INSPECT"
  },
  {
    "tokens": [
      "Δώσε",
      "το",
      "μεγάλο"
    ],
    "tags": [
      "O",
      "O",
      "B-SIZE"
    ],
    "intent": "GIVE"
  },
  {
    "tokens": [
      "Φέρτε",
      "τη",
      "οξύμετρο",
      "5ml",
      "από",
      "την",
      "Αποθήκη"
    ],
    "tags": [
      "O",
      "O",
      "B-TYPE",
      "B-SIZE",
      "O",
      "O",
      "B-ZONE"
    ],
    "intent": "FETCH"
  },
  {
    "tokens": [
      "Ξεκλείδωσε",
      "το",
      "κουτί",
      "στη",
      "Αποθήκη"
    ],
    "tags": [
      "O",
      "O",
      "B-TYPE",
      "O",
      "B-ZONE"
    ],
    "intent": "OPEN"
  },
  {
    "tokens": [
      "Χορήγησε",
      "το",
      "παρακεταμόλη"
    ],
    "tags": [
      "O",
      "O",
      "B-TYPE"
    ],
    "intent": "GIVE"
  },
  {
    "tokens": [
      "Κλείσε",
      "το",
      "κουτί"
    ],
    "tags": [
      "O",
      "O",
      "B-TYPE"
    ],
    "intent": "CLOSE"
  },
  {
    "tokens": [
      "Ξεκλείδωσε",
      "το",
      "κουτί",
      "στη",
      "Φαρμακείο"
    ],
    "tags": [
      "O",
      "O",
      "B-TYPE",
      "O",
      "B-ZONE"
    ],
    "intent": "OPEN"
  },
  {
    "tokens": [
      "Ξεκλείδωσε",
      "το",
      "κουτί",
      "στη",
      "Αποθήκη"
    ],
    "tags": [
      "O",
      "O",
      "B-TYPE",
      "O",
      "B-ZONE"
    ],
    "intent": "OPEN"
  },
  {
    "tokens": [
      "Δώσε",
      "το",
      "γάζα"
    ],
    "tags": [
      "O",
      "O",
      "B-TYPE"
    ],
    "intent": "GIVE"
  },
  {
    "tokens": [
      "Φέρε",
      "τη",
      "επίδεσμος",
      "5x5",
      "από",
      "την",
      "Φαρμακείο"
    ],
    "tags": [
      "O",
      "O",
      "B-TYPE",
      "B-SIZE",
      "O",
      "O",
      "B-ZONE"
    ],
    "intent": "FETCH"
  },
  {
    "tokens": [
      "Αποθήκη",
      "γάζες"
    ],
    "tags": [
      "B-ZONE",
      "B-TYPE"
    ],
    "intent": "FETCH"
  },
  {
    "tokens": [
      "Κλείσε",
      "το",
      "κουτί"
    ],
    "tags": [
      "O",
      "O",
      "B-TYPE"
    ],
    "intent": "CLOSE"
  },
  {
    "tokens": [
      "Ξεκλείδωσε",
      "το",
      "κουτί",
      "στη",
      "ΜΕΘ"
    ],
    "tags": [
      "O",
      "O",
      "B-TYPE",
      "O",
      "B-ZONE"
    ],
    "intent": "OPEN"
  },
  {
    "tokens": [
      "Έλεγξε",
      "τα",
      "ληγμένα"
    ],
    "tags": [
      "O",
      "O",
      "B-STATE"
    ],
    "intent": "INSPECT"
  },
  {
    "tokens": [
      "Ξεκλείδωσε",
      "το",
      "κουτί",
      "στη",
      "Θάλαμος"
    ],
    "tags": [
      "O",
      "O",
      "B-TYPE",
      "O",
      "B-ZONE"
    ],
    "intent": "OPEN"
  },
  {
    "tokens": [
      "Βάλε",
      "το",
      "ιβουπροφένη",
      "ληγμένη"
    ],
    "tags": [
      "O",
      "O",
      "B-TYPE",
      "B-STATE"
    ],
    "intent": "PLACE"
  },
  {
    "tokens": [
      "Δώσε",
      "το",
      "αντιβιοτικό"
    ],
    "tags": [
      "O",
      "O",
      "B-TYPE"
    ],
    "intent": "GIVE"
  },
  {
    "tokens": [
      "Φέρε",
      "μου",
      "τη",
      "σφυγμόμετρο",
      "μικρό",
      "από",
      "την",
      "Φαρμακείο"
    ],
    "tags": [
      "O",
      "O",
      "O",
      "B-TYPE",
      "B-SIZE",
      "O",
      "O",
      "B-ZONE"
    ],
    "intent": "FETCH"
  },
  {
    "tokens": [
      "Δώσε",
      "το",
      "ιβουπροφένη"
    ],
    "tags": [
      "O",
      "O",
      "B-TYPE"
    ],
    "intent": "GIVE"
  },
  {
    "tokens": [
      "Δες",
      "το",
      "κουτί"
    ],
    "tags": [
      "O",
      "O",
      "B-TYPE"
    ],
    "intent": "INSPECT"
  },
  {
    "tokens": [
      "Έλεγξε",
      "το",
      "βελόνα"
    ],
    "tags": [
      "O",
      "O",
      "B-TYPE"
    ],
    "intent": "INSPECT"
  },
  {
    "tokens": [
      "Παρακεταμόλη",
      "ΜΕΘ"
    ],
    "tags": [
      "B-TYPE",
      "B-ZONE"
    ],
    "intent": "FETCH"
  },
  {
    "tokens": [
      "Παρακεταμόλη",
      "ΜΕΘ"
    ],
    "tags": [
      "B-TYPE",
      "B-ZONE"
    ],
    "intent": "FETCH"
  },
  {
    "tokens": [
      "Δες",
      "το",
      "οξύμετρο"
    ],
    "tags": [
      "O",
      "O",
      "B-TYPE"
    ],
    "intent": "INSPECT"
  },
  {
    "tokens": [
      "Φέρε",
      "το",
      "μικρό"
    ],
    "tags": [
      "O",
      "O",
      "B-SIZE"
    ],
    "intent": "FETCH"
  },
  {
    "tokens": [
      "Τοποθέτησε",
      "το",
      "επίδεσμο",
      "ληγμένο"
    ],
    "tags": [
      "O",
      "O",
      "B-TYPE",
      "B-STATE"
    ],
    "intent": "PLACE"
  },
  {
    "tokens": [
      "Δώσε",
      "το",
      "μεγάλο"
    ],
    "tags": [
      "O",
      "O",
      "B-SIZE"
    ],
    "intent": "GIVE"
  },
  {
    "tokens": [
      "Βάλε",
      "το",
      "σύριγγα",
      "ανοιχτή"
    ],
    "tags": [
      "O",
      "O",
      "B-TYPE",
      "B-STATE"
    ],
    "intent": "PLACE"
  },
  {
    "tokens": [
      "Φέρε",
      "τη",
      "γάζες",
      "μεγάλο",
      "από",
      "την",
      "ΜΕΘ"
    ],
    "tags": [
      "O",
      "O",
      "B-TYPE",
      "B-SIZE",
      "O",
      "O",
      "B-ZONE"
    ],
    "intent": "FETCH"
  },
  {
    "tokens": [
      "Δώσε",
      "το",
      "ιβουπροφένη"
    ],
    "tags": [
      "O",
      "O",
      "B-TYPE"
    ],
    "intent": "GIVE"
  },
  {
    "tokens": [
      "Άνοιξε",
      "το",
      "κουτί",
      "στη",
      "Φαρμακείο"
    ],
    "tags": [
      "O",
      "O",
      "B-TYPE",
      "O",
      "B-ZONE"
    ],
    "intent": "OPEN"
  },
  {
    "tokens": [
      "Ξεκλείδωσε",
      "το",
      "κουτί",
      "στη",
      "ΜΕΘ"
    ],
    "tags": [
      "O",
      "O",
      "B-TYPE",
      "O",
      "B-ZONE"
    ],
    "intent": "OPEN"
  },
  {
    "tokens": [
      "Φέρτε",
      "τη",
      "οξύμετρο",
      "μεσαίο",
      "από",
      "την",
      "Φαρμακείο"
    ],
    "tags": [
      "O",
      "O",
      "B-TYPE",
      "B-SIZE",
      "O",
      "O",
      "B-ZONE"
    ],
    "intent": "FETCH"
  },
  {
    "tokens": [
      "Άφησε",
      "το",
      "επίδεσμος",
      "αποστειρωμένο"
    ],
    "tags": [
      "O",
      "O",
      "B-TYPE",
      "B-STATE"
    ],
    "intent": "PLACE"
  },
  {
    "tokens": [
      "Δες",
      "το",
      "βελόνα"
    ],
    "tags": [
      "O",
      "O",
      "B-TYPE"
    ],
    "intent": "INSPECT"
  },
  {
    "tokens": [
      "Ξεκλείδωσε",
      "το",
      "κουτί",
      "στη",
      "ΜΕΘ"
    ],
    "tags": [
      "O",
      "O",
      "B-TYPE",
      "O",
      "B-ZONE"
    ],
    "intent": "OPEN"
  },
  {
    "tokens": [
      "Τοποθέτησε",
      "το",
      "κουτί",
      "αποστειρωμένη"
    ],
    "tags": [
      "O",
      "O",
      "B-TYPE",
      "B-STATE"
    ],
    "intent": "PLACE"
  },
  {
    "tokens": [
      "Φέρτε",
      "τη",
      "κουτί",
      "μικρή",
      "από",
      "την",
      "Θάλαμος"
    ],
    "tags": [
      "O",
      "O",
      "B-TYPE",
      "B-SIZE",
      "O",
      "O",
      "B-ZONE"
    ],
    "intent": "FETCH"
  },
  {
    "tokens": [
      "Παρέδωσε",
      "τη",
      "σύριγγα",
      "5x5",
      "από",
      "την",
      "Φαρμακείο"
    ],
    "tags": [
      "O",
      "O",
      "B-TYPE",
      "B-SIZE",
      "O",
      "O",
      "B-ZONE"
    ],
    "intent": "FETCH"
  },
  {
    "tokens": [
      "Εξέτασε",
      "το",
      "σφυγμόμετρο"
    ],
    "tags": [
      "O",
      "O",
      "B-TYPE"
    ],
    "intent": "INSPECT"
  },
  {
    "tokens": [
      "Κλείσε",
      "το",
      "κουτί"
    ],
    "tags": [
      "O",
      "O",
      "B-TYPE"
    ],
    "intent": "CLOSE"
  },
  {
    "tokens": [
      "Δώσε",
      "το",
      "γάζα"
    ],
    "tags": [
      "O",
      "O",
      "B-TYPE"
    ],
    "intent": "GIVE"
  },
  {
    "tokens": [
      "Δώσε",
      "το",
      "γάζα"
    ],
    "tags": [
      "O",
      "O",
      "B-TYPE"
    ],
    "intent": "GIVE"
  },
  {
    "tokens": [
      "Δες",
      "το",
      "γάζες"
    ],
    "tags": [
      "O",
      "O",
      "B-TYPE"
    ],
    "intent": "INSPECT"
  },
  {
    "tokens": [
      "Χορήγησε",
      "το",
      "ιβουπροφένη"
    ],
    "tags": [
      "O",
      "O",
      "B-TYPE"
    ],
    "intent": "GIVE"
  },
  {
    "tokens": [
      "Άφησε",
      "το",
      "θερμόμετρο",
      "ληγμένο"
    ],
    "tags": [
      "O",
      "O",
      "B-TYPE",
      "B-STATE"
    ],
    "intent": "PLACE"
  },
  {
    "tokens": [
      "Παρέδωσε",
      "τη",
      "σφυγμόμετρο",
      "μεσαία",
      "από",
      "την",
      "Θάλαμος"
    ],
    "tags": [
      "O",
      "O",
      "B-TYPE",
      "B-SIZE",
      "O",
      "O",
      "B-ZONE"
    ],
    "intent": "FETCH"
  },
  {
    "tokens": [
      "Πάρε",
      "τη",
      "θερμόμετρο",
      "μικρή",
      "από",
      "την",
      "Φαρμακείο"
    ],
    "tags": [
      "O",
      "O",
      "B-TYPE",
      "B-SIZE",
      "O",
      "O",
      "B-ZONE"
    ],
    "intent": "FETCH"
  },
  {
    "tokens": [
      "Χορήγησε",
      "το",
      "γάζα"
    ],
    "tags": [
      "O",
      "O",
      "B-TYPE"
    ],
    "intent": "GIVE"
  },
  {
    "tokens": [
      "Κλείσε",
      "το",
      "κουτί"
    ],
    "tags": [
      "O",
      "O",
      "B-TYPE"
    ],
    "intent": "CLOSE"
  },
  {
    "tokens": [
      "Εξέτασε",
      "το",
      "βελόνα"
    ],
    "tags": [
      "O",
      "O",
      "B-TYPE"
    ],
    "intent": "INSPECT"
  },
  {
    "tokens": [
      "Δώσε",
      "το",
      "μεγάλο"
    ],
    "tags": [
      "O",
      "O",
      "B-SIZE"
    ],
    "intent": "GIVE"
  },
  {
    "tokens": [
      "Κλείσε",
      "το",
      "κουτί"
    ],
    "tags": [
      "O",
      "O",
      "B-TYPE"
    ],
    "intent": "CLOSE"
  },
  {
    "tokens": [
      "Φέρε",
      "τη",
      "οξύμετρο",
      "5x5",
      "από",
      "την",
      "Φαρμακείο"
    ],
    "tags": [
      "O",
      "O",
      "B-TYPE",
      "B-SIZE",
      "O",
      "O",
      "B-ZONE"
    ],
    "intent": "FETCH"
  },
  {
    "tokens": [
      "Τσέκαρε",
      "το",
      "σύριγγα"
    ],
    "tags": [
      "O",
      "O",
      "B-TYPE"
    ],
    "intent": "INSPECT"
  },
  {
    "tokens": [
      "Πάρε",
      "τη",
      "επίδεσμος",
      "μικρό",
      "από",
      "την",
      "Αποθήκη"
    ],
    "tags": [
      "O",
      "O",
      "B-TYPE",
      "B-SIZE",
      "O",
      "O",
      "B-ZONE"
    ],
    "intent": "FETCH"
  },
  {
    "tokens": [
      "Κλείστο"
    ],
    "tags": [
      "O"
    ],
    "intent": "CLOSE"
  },
  {
    "tokens": [
      "Δώσε",
      "το",
      "μεγάλο"
    ],
    "tags": [
      "O",
      "O",
      "B-SIZE"
    ],
    "intent": "GIVE"
  },
  {
    "tokens": [
      "Φέρε",
      "τη",
      "επίδεσμος",
      "μεσαίο",
      "από",
      "την",
      "Φαρμακείο"
    ],
    "tags": [
      "O",
      "O",
      "B-TYPE",
      "B-SIZE",
      "O",
      "O",
      "B-ZONE"
    ],
    "intent": "FETCH"
  },
  {
    "tokens": [
      "Φέρε",
      "μου",
      "τη",
      "σφυγμόμετρο",
      "10ml",
      "από",
      "την",
      "Αποθήκη"
    ],
    "tags": [
      "O",
      "O",
      "O",
      "B-TYPE",
      "B-SIZE",
      "O",
      "O",
      "B-ZONE"
    ],
    "intent": "FETCH"
  },
  {
    "tokens": [
      "Βελόνα",
      "21g"
    ],
    "tags": [
      "B-TYPE",
      "B-SIZE"
    ],
    "intent": "FETCH"
  },
  {
    "tokens": [
      "Φέρτε",
      "τη",
      "οξύμετρο",
      "5ml",
      "από",
      "την",
      "Αποθήκη"
    ],
    "tags": [
      "O",
      "O",
      "B-TYPE",
      "B-SIZE",
      "O",
      "O",
      "B-ZONE"
    ],
    "intent": "FETCH"
  },
  {
    "tokens": [
      "Ξεκλείδωσε",
      "το",
      "κουτί",
      "στη",
      "Θάλαμος"
    ],
    "tags": [
      "O",
      "O",
      "B-TYPE",
      "O",
      "B-ZONE"
    ],
    "intent": "OPEN"
  },
  {
    "tokens": [
      "Χορήγησε",
      "το",
      "παρακεταμόλη"
    ],
    "tags": [
      "O",
      "O",
      "B-TYPE"
    ],
    "intent": "GIVE"
  },
  {
    "tokens": [
      "Κλείσε",
      "το",
      "κουτί"
    ],
    "tags": [
      "O",
      "O",
      "B-TYPE"
    ],
    "intent": "CLOSE"
  },
  {
    "tokens": [
      "Βάλε",
      "αυτό",
      "εδώ"
    ],
    "tags": [
      "O",
      "O",
      "O"
    ],
    "intent": "PLACE"
  },
  {
    "tokens": [
      "Άφησε",
      "το",
      "σύριγγα",
      "ληγμένο"
    ],
    "tags": [
      "O",
      "O",
      "B-TYPE",
      "B-STATE"
    ],
    "intent": "PLACE"
  },
  {
    "tokens": [
      "Δώσε",
      "το",
      "γάζα"
    ],
    "tags": [
      "O",
      "O",
      "B-TYPE"
    ],
    "intent": "GIVE"
  },
  {
    "tokens": [
      "Τη",
      "μεγάλη",
      "γάζα"
    ],
    "tags": [
      "O",
      "B-SIZE",
      "B-TYPE"
    ],
    "intent": "FETCH"
  },
  {
    "tokens": [
      "Βάλε",
      "το",
      "σύριγγα",
      "ληγμένο"
    ],
    "tags": [
      "O",
      "O",
      "B-TYPE",
      "B-STATE"
    ],
    "intent": "PLACE"
  },
  {
    "tokens": [
      "Έλεγξε",
      "το",
      "κουτί"
    ],
    "tags": [
      "O",
      "O",
      "B-TYPE"
    ],
    "intent": "INSPECT"
  },
  {
    "tokens": [
      "Κλείσε",
      "το",
      "κουτί"
    ],
    "tags": [
      "O",
      "O",
      "B-TYPE"
    ],
    "intent": "CLOSE"
  },
  {
    "tokens": [
      "Ληγμένο",
      "είναι;"
    ],
    "tags": [
      "B-STATE",
      "O"
    ],
    "intent": "INSPECT"
  },
  {
    "tokens": [
      "Φέρε",
      "τη",
      "επίδεσμο",
      "10x10",
      "από",
      "την",
      "Αποθήκη"
    ],
    "tags": [
      "O",
      "O",
      "B-TYPE",
      "B-SIZE",
      "O",
      "O",
      "B-ZONE"
    ],
    "intent": "FETCH"
  },
  {
    "tokens": [
      "Φέρε",
      "μου",
      "τη",
      "θερμόμετρο",
      "μικρή",
      "από",
      "την",
      "Αποθήκη"
    ],
    "tags": [
      "O",
      "O",
      "O",
      "B-TYPE",
      "B-SIZE",
      "O",
      "O",
      "B-ZONE"
    ],
    "intent": "FETCH"
  },
  {
    "tokens": [
      "Χορήγησε",
      "το",
      "αντιβιοτικό"
    ],
    "tags": [
      "O",
      "O",
      "B-TYPE"
    ],
    "intent": "GIVE"
  },
  {
    "tokens": [
      "Έλεγξε",
      "τα",
      "ληγμένα"
    ],
    "tags": [
      "O",
      "O",
      "B-STATE"
    ],
    "intent": "INSPECT"
  },
  {
    "tokens": [
      "Παρακεταμόλη",
      "ΜΕΘ"
    ],
    "tags": [
      "B-TYPE",
      "B-ZONE"
    ],
    "intent": "FETCH"
  },
  {
    "tokens": [
      "Αποθήκη",
      "γάζες"
    ],
    "tags": [
      "B-ZONE",
      "B-TYPE"
    ],
    "intent": "FETCH"
  },
  {
    "tokens": [
      "Παρακεταμόλη",
      "ΜΕΘ"
    ],
    "tags": [
      "B-TYPE",
      "B-ZONE"
    ],
    "intent": "FETCH"
  },
  {
    "tokens": [
      "Αποθήκη",
      "γάζες"
    ],
    "tags": [
      "B-ZONE",
      "B-TYPE"
    ],
    "intent": "FETCH"
  },
  {
    "tokens": [
      "Έλεγξε",
      "το",
      "επίδεσμος"
    ],
    "tags": [
      "O",
      "O",
      "B-TYPE"
    ],
    "intent": "INSPECT"
  },
  {
    "tokens": [
      "Παρέδωσε",
      "τη",
      "παρακεταμόλη",
      "μεσαία",
      "από",
      "την",
      "Θάλαμος"
    ],
    "tags": [
      "O",
      "O",
      "B-TYPE",
      "B-SIZE",
      "O",
      "O",
      "B-ZONE"
    ],
    "intent": "FETCH"
  },
  {
    "tokens": [
      "Κλείσε",
      "το",
      "κουτί"
    ],
    "tags": [
      "O",
      "O",
      "B-TYPE"
    ],
    "intent": "CLOSE"
  },
  {
    "tokens": [
      "Φέρε",
      "το",
      "μικρό"
    ],
    "tags": [
      "O",
      "O",
      "B-SIZE"
    ],
    "intent": "FETCH"
  },
  {
    "tokens": [
      "Εξέτασε",
      "το",
      "σφυγμόμετρο"
    ],
    "tags": [
      "O",
      "O",
      "B-TYPE"
    ],
    "intent": "INSPECT"
  },
  {
    "tokens": [
      "Κλείστο"
    ],
    "tags": [
      "O"
    ],
    "intent": "CLOSE"
  },
  {
    "tokens": [
      "Δες",
      "το",
      "θερμόμετρο"
    ],
    "tags": [
      "O",
      "O",
      "B-TYPE"
    ],
    "intent": "INSPECT"
  },
  {
    "tokens": [
      "Τοποθέτησε",
      "το",
      "βελόνα",
      "ανοιχτό"
    ],
    "tags": [
      "O",
      "O",
      "B-TYPE",
      "B-STATE"
    ],
    "intent": "PLACE"
  },
  {
    "tokens": [
      "Κλείσε",
      "το",
      "κουτί"
    ],
    "tags": [
      "O",
      "O",
      "B-TYPE"
    ],
    "intent": "CLOSE"
  },
  {
    "tokens": [
      "Χορήγησε",
      "το",
      "παρακεταμόλη"
    ],
    "tags": [
      "O",
      "O",
      "B-TYPE"
    ],
    "intent": "GIVE"
  },
  {
    "tokens": [
      "Άνοιξε",
      "το",
      "κουτί",
      "στη",
      "Φαρμακείο"
    ],
    "tags": [
      "O",
      "O",
      "B-TYPE",
      "O",
      "B-ZONE"
    ],
    "intent": "OPEN"
  },
  {
    "tokens": [
      "Χορήγησε",
      "το",
      "αντιβιοτικό"
    ],
    "tags": [
      "O",
      "O",
      "B-TYPE"
    ],
    "intent": "GIVE"
  },
  {
    "tokens": [
      "Δώσε",
      "το",
      "γάζα"
    ],
    "tags": [
      "O",
      "O",
      "B-TYPE"
    ],
    "intent": "GIVE"
  },
  {
    "tokens": [
      "Δώσε",
      "το",
      "μεγάλο"
    ],
    "tags": [
      "O",
      "O",
      "B-SIZE"
    ],
    "intent": "GIVE"
  },
  {
    "tokens": [
      "Χορήγησε",
      "το",
      "παρακεταμόλη"
    ],
    "tags": [
      "O",
      "O",
      "B-TYPE"
    ],
    "intent": "GIVE"
  },
  {
    "tokens": [
      "Άνοιξε",
      "το",
      "κουτί",
      "στη",
      "ΜΕΘ"
    ],
    "tags": [
      "O",
      "O",
      "B-TYPE",
      "O",
      "B-ZONE"
    ],
    "intent": "OPEN"
  },
  {
    "tokens": [
      "Κλείστο"
    ],
    "tags": [
      "O"
    ],
    "intent": "CLOSE"
  },
  {
    "tokens": [
      "Έλεγξε",
      "το",
      "κουτί"
    ],
    "tags": [
      "O",
      "O",
      "B-TYPE"
    ],
    "intent": "INSPECT"
  },
  {
    "tokens": [
      "Έλεγξε",
      "τα",
      "ληγμένα"
    ],
    "tags": [
      "O",
      "O",
      "B-STATE"
    ],
    "intent": "INSPECT"
  },
  {
    "tokens": [
      "Βάλε",
      "το",
      "παρακεταμόλη",
      "ανοιχτή"
    ],
    "tags": [
      "O",
      "O",
      "B-TYPE",
      "B-STATE"
    ],
    "intent": "PLACE"
  },
  {
    "tokens": [
      "Φέρε",
      "τη",
      "θερμόμετρο",
      "10ml",
      "από",
      "την",
      "ΜΕΘ"
    ],
    "tags": [
      "O",
      "O",
      "B-TYPE",
      "B-SIZE",
      "O",
      "O",
      "B-ZONE"
    ],
    "intent": "FETCH"
  },
  {
    "tokens": [
      "Ξεκλείδωσε",
      "το",
      "κουτί",
      "στη",
      "Θάλαμος"
    ],
    "tags": [
      "O",
      "O",
      "B-TYPE",
      "O",
      "B-ZONE"
    ],
    "intent": "OPEN"
  },
  {
    "tokens": [
      "Βελόνα",
      "21g"
    ],
    "tags": [
      "B-TYPE",
      "B-SIZE"
    ],
    "intent": "FETCH"
  },
  {
    "tokens": [
      "Δες",
      "το",
      "σύριγγα"
    ],
    "tags": [
      "O",
      "O",
      "B-TYPE"
    ],
    "intent": "INSPECT"
  },
  {
    "tokens": [
      "Βάλε",
      "το",
      "κουτί",
      "αποστειρωμένη"
    ],
    "tags": [
      "O",
      "O",
      "B-TYPE",
      "B-STATE"
    ],
    "intent": "PLACE"
  },
  {
    "tokens": [
      "Ξεκλείδωσε",
      "το",
      "κουτί",
      "στη",
      "Αποθήκη"
    ],
    "tags": [
      "O",
      "O",
      "B-TYPE",
      "O",
      "B-ZONE"
    ],
    "intent": "OPEN"
  },
  {
    "tokens": [
      "Άνοιξε",
      "το"
    ],
    "tags": [
      "O",
      "O"
    ],
    "intent": "OPEN"
  },
  {
    "tokens": [
      "Παρακεταμόλη",
      "ΜΕΘ"
    ],
    "tags": [
      "B-TYPE",
      "B-ZONE"
    ],
    "intent": "FETCH"
  },
  {
    "tokens": [
      "Φέρε",
      "μου",
      "τη",
      "επίδεσμος",
      "500mg",
      "από",
      "την",
      "Φαρμακείο"
    ],
    "tags": [
      "O",
      "O",
      "O",
      "B-TYPE",
      "B-SIZE",
      "O",
      "O",
      "B-ZONE"
    ],
    "intent": "FETCH"
  },
  {
    "tokens": [
      "Βάλε",
      "αυτό",
      "εδώ"
    ],
    "tags": [
      "O",
      "O",
      "O"
    ],
    "intent": "PLACE"
  },
  {
    "tokens": [
      "Φέρε",
      "μου",
      "τη",
      "αντιβιοτικό",
      "μεγάλη",
      "από",
      "την",
      "Αποθήκη"
    ],
    "tags": [
      "O",
      "O",
      "O",
      "B-TYPE",
      "B-SIZE",
      "O",
      "O",
      "B-ZONE"
    ],
    "intent": "FETCH"
  },
  {
    "tokens": [
      "Πάρε",
      "τη",
      "βελόνα",
      "μεγάλο",
      "από",
      "την",
      "ΜΕΘ"
    ],
    "tags": [
      "O",
      "O",
      "B-TYPE",
      "B-SIZE",
      "O",
      "O",
      "B-ZONE"
    ],
    "intent": "FETCH"
  },
  {
    "tokens": [
      "Άνοιξε",
      "το",
      "κουτί",
      "στη",
      "Φαρμακείο"
    ],
    "tags": [
      "O",
      "O",
      "B-TYPE",
      "O",
      "B-ZONE"
    ],
    "intent": "OPEN"
  },
  {
    "tokens": [
      "Ξεκλείδωσε",
      "το",
      "κουτί",
      "στη",
      "Αποθήκη"
    ],
    "tags": [
      "O",
      "O",
      "B-TYPE",
      "O",
      "B-ZONE"
    ],
    "intent": "OPEN"
  },
  {
    "tokens": [
      "Κλείσε",
      "το",
      "κουτί"
    ],
    "tags": [
      "O",
      "O",
      "B-TYPE"
    ],
    "intent": "CLOSE"
  },
  {
    "tokens": [
      "Φέρε",
      "μου",
      "τη",
      "κουτί",
      "μεσαίο",
      "από",
      "την",
      "Αποθήκη"
    ],
    "tags": [
      "O",
      "O",
      "O",
      "B-TYPE",
      "B-SIZE",
      "O",
      "O",
      "B-ZONE"
    ],
    "intent": "FETCH"
  },
  {
    "tokens": [
      "Παρακεταμόλη",
      "ΜΕΘ"
    ],
    "tags": [
      "B-TYPE",
      "B-ZONE"
    ],
    "intent": "FETCH"
  },
  {
    "tokens": [
      "Τη",
      "μεγάλη",
      "γάζα"
    ],
    "tags": [
      "O",
      "B-SIZE",
      "B-TYPE"
    ],
    "intent": "FETCH"
  },
  {
    "tokens": [
      "Έλεγξε",
      "το",
      "οξύμετρο"
    ],
    "tags": [
      "O",
      "O",
      "B-TYPE"
    ],
    "intent": "INSPECT"
  },
  {
    "tokens": [
      "Φέρτε",
      "τη",
      "ιβουπροφένη",
      "500mg",
      "από",
      "την",
      "Φαρμακείο"
    ],
    "tags": [
      "O",
      "O",
      "B-TYPE",
      "B-SIZE",
      "O",
      "O",
      "B-ZONE"
    ],
    "intent": "FETCH"
  },
  {
    "tokens": [
      "Τοποθέτησε",
      "το",
      "ιβουπροφένη",
      "αποστειρωμένο"
    ],
    "tags": [
      "O",
      "O",
      "B-TYPE",
      "B-STATE"
    ],
    "intent": "PLACE"
  },
  {
    "tokens": [
      "Δες",
      "το",
      "ιβουπροφένη"
    ],
    "tags": [
      "O",
      "O",
      "B-TYPE"
    ],
    "intent": "INSPECT"
  },
  {
    "tokens": [
      "Άνοιξε",
      "το",
      "κουτί",
      "στη",
      "ΜΕΘ"
    ],
    "tags": [
      "O",
      "O",
      "B-TYPE",
      "O",
      "B-ZONE"
    ],
    "intent": "OPEN"
  },
  {
    "tokens": [
      "Τη",
      "μεγάλη",
      "γάζα"
    ],
    "tags": [
      "O",
      "B-SIZE",
      "B-TYPE"
    ],
    "intent": "FETCH"
  },
  {
    "tokens": [
      "Άφησε",
      "το",
      "γάζα",
      "ληγμένο"
    ],
    "tags": [
      "O",
      "O",
      "B-TYPE",
      "B-STATE"
    ],
    "intent": "PLACE"
  },
  {
    "tokens": [
      "Φέρε",
      "μου",
      "τη",
      "θερμόμετρο",
      "μεγάλη",
      "από",
      "την",
      "Φαρμακείο"
    ],
    "tags": [
      "O",
      "O",
      "O",
      "B-TYPE",
      "B-SIZE",
      "O",
      "O",
      "B-ZONE"
    ],
    "intent": "FETCH"
  },
  {
    "tokens": [
      "Βάλε",
      "το",
      "γάζες",
      "ανοιχτή"
    ],
    "tags": [
      "O",
      "O",
      "B-TYPE",
      "B-STATE"
    ],
    "intent": "PLACE"
  },
  {
    "tokens": [
      "Άφησε",
      "το",
      "θερμόμετρο",
      "αποστειρωμένο"
    ],
    "tags": [
      "O",
      "O",
      "B-TYPE",
      "B-STATE"
    ],
    "intent": "PLACE"
  },
  {
    "tokens": [
      "Άφησε",
      "το",
      "ιβουπροφένη",
      "ληγμένη"
    ],
    "tags": [
      "O",
      "O",
      "B-TYPE",
      "B-STATE"
    ],
    "intent": "PLACE"
  },
  {
    "tokens": [
      "Ξεκλείδωσε",
      "το",
      "κουτί",
      "στη",
      "Θάλαμος"
    ],
    "tags": [
      "O",
      "O",
      "B-TYPE",
      "O",
      "B-ZONE"
    ],
    "intent": "OPEN"
  },
  {
    "tokens": [
      "Ξεκλείδωσε",
      "το",
      "κουτί",
      "στη",
      "Φαρμακείο"
    ],
    "tags": [
      "O",
      "O",
      "B-TYPE",
      "O",
      "B-ZONE"
    ],
    "intent": "OPEN"
  },
  {
    "tokens": [
      "Φέρτε",
      "τη",
      "αντιβιοτικό",
      "1ml",
      "από",
      "την",
      "Αποθήκη"
    ],
    "tags": [
      "O",
      "O",
      "B-TYPE",
      "B-SIZE",
      "O",
      "O",
      "B-ZONE"
    ],
    "intent": "FETCH"
  },
  {
    "tokens": [
      "Πάρε",
      "τη",
      "γάζες",
      "21g",
      "από",
      "την",
      "Αποθήκη"
    ],
    "tags": [
      "O",
      "O",
      "B-TYPE",
      "B-SIZE",
      "O",
      "O",
      "B-ZONE"
    ],
    "intent": "FETCH"
  },
  {
    "tokens": [
      "Πάρε",
      "τη",
      "γάζα",
      "μικρή",
      "από",
      "την",
      "Φαρμακείο"
    ],
    "tags": [
      "O",
      "O",
      "B-TYPE",
      "B-SIZE",
      "O",
      "O",
      "B-ZONE"
    ],
    "intent": "FETCH"
  },
  {
    "tokens": [
      "Φέρε",
      "τη",
      "γάζα",
      "μικρή",
      "από",
      "την",
      "Θάλαμος"
    ],
    "tags": [
      "O",
      "O",
      "B-TYPE",
      "B-SIZE",
      "O",
      "O",
      "B-ZONE"
    ],
    "intent": "FETCH"
  },
  {
    "tokens": [
      "Άνοιξε",
      "το"
    ],
    "tags": [
      "O",
      "O"
    ],
    "intent": "OPEN"
  },
  {
    "tokens": [
      "Παρέδωσε",
      "τη",
      "οξύμετρο",
      "μεγάλο",
      "από",
      "την",
      "Θάλαμος"
    ],
    "tags": [
      "O",
      "O",
      "B-TYPE",
      "B-SIZE",
      "O",
      "O",
      "B-ZONE"
    ],
    "intent": "FETCH"
  },
  {
    "tokens": [
      "Πάρε",
      "τη",
      "κουτί",
      "10ml",
      "από",
      "την",
      "Θάλαμος"
    ],
    "tags": [
      "O",
      "O",
      "B-TYPE",
      "B-SIZE",
      "O",
      "O",
      "B-ZONE"
    ],
    "intent": "FETCH"
  },
  {
    "tokens": [
      "Πάρε",
      "τη",
      "παρακεταμόλη",
      "500mg",
      "από",
      "την",
      "Αποθήκη"
    ],
    "tags": [
      "O",
      "O",
      "B-TYPE",
      "B-SIZE",
      "O",
      "O",
      "B-ZONE"
    ],
    "intent": "FETCH"
  },
  {
    "tokens": [
      "Φέρε",
      "τη",
      "σύριγγα",
      "μικρή",
      "από",
      "την",
      "ΜΕΘ"
    ],
    "tags": [
      "O",
      "O",
      "B-TYPE",
      "B-SIZE",
      "O",
      "O",
      "B-ZONE"
    ],
    "intent": "FETCH"
  },
  {
    "tokens": [
      "Δώσε",
      "εκείνο"
    ],
    "tags": [
      "O",
      "O"
    ],
    "intent": "GIVE"
  },
  {
    "tokens": [
      "Αποθήκη",
      "γάζες"
    ],
    "tags": [
      "B-ZONE",
      "B-TYPE"
    ],
    "intent": "FETCH"
  },
  {
    "tokens": [
      "Τη",
      "μεγάλη",
      "γάζα"
    ],
    "tags": [
      "O",
      "B-SIZE",
      "B-TYPE"
    ],
    "intent": "FETCH"
  },
  {
    "tokens": [
      "Παρέδωσε",
      "τη",
      "σύριγγα",
      "10x10",
      "από",
      "την",
      "Φαρμακείο"
    ],
    "tags": [
      "O",
      "O",
      "B-TYPE",
      "B-SIZE",
      "O",
      "O",
      "B-ZONE"
    ],
    "intent": "FETCH"
  },
  {
    "tokens": [
      "Δες",
      "το",
      "παρακεταμόλη"
    ],
    "tags": [
      "O",
      "O",
      "B-TYPE"
    ],
    "intent": "INSPECT"
  },
  {
    "tokens": [
      "Δώσε",
      "το",
      "παρακεταμόλη"
    ],
    "tags": [
      "O",
      "O",
      "B-TYPE"
    ],
    "intent": "GIVE"
  },
  {
    "tokens": [
      "Τσέκαρε",
      "το",
      "παρακεταμόλη"
    ],
    "tags": [
      "O",
      "O",
      "B-TYPE"
    ],
    "intent": "INSPECT"
  },
  {
    "tokens": [
      "Δώσε",
      "εκείνο"
    ],
    "tags": [
      "O",
      "O"
    ],
    "intent": "GIVE"
  },
  {
    "tokens": [
      "Εξέτασε",
      "το",
      "θερμόμετρο"
    ],
    "tags": [
      "O",
      "O",
      "B-TYPE"
    ],
    "intent": "INSPECT"
  },
  {
    "tokens": [
      "Πάρε",
      "τη",
      "παρακεταμόλη",
      "μεγάλο",
      "από",
      "την",
      "ΜΕΘ"
    ],
    "tags": [
      "O",
      "O",
      "B-TYPE",
      "B-SIZE",
      "O",
      "O",
      "B-ZONE"
    ],
    "intent": "FETCH"
  },
  {
    "tokens": [
      "Άφησε",
      "το",
      "επίδεσμος",
      "ανοιχτή"
    ],
    "tags": [
      "O",
      "O",
      "B-TYPE",
      "B-STATE"
    ],
    "intent": "PLACE"
  },
  {
    "tokens": [
      "Φέρτε",
      "τη",
      "κουτί",
      "21g",
      "από",
      "την",
      "Φαρμακείο"
    ],
    "tags": [
      "O",
      "O",
      "B-TYPE",
      "B-SIZE",
      "O",
      "O",
      "B-ZONE"
    ],
    "intent": "FETCH"
  },
  {
    "tokens": [
      "Ληγμένο",
      "είναι;"
    ],
    "tags": [
      "B-STATE",
      "O"
    ],
    "intent": "INSPECT"
  },
  {
    "tokens": [
      "Σύριγγα",
      "1ml"
    ],
    "tags": [
      "B-TYPE",
      "B-SIZE"
    ],
    "intent": "FETCH"
  },
  {
    "tokens": [
      "Αποθήκη",
      "γάζες"
    ],
    "tags": [
      "B-ZONE",
      "B-TYPE"
    ],
    "intent": "FETCH"
  },
  {
    "tokens": [
      "Πάρε",
      "τη",
      "αντιβιοτικό",
      "μικρό",
      "από",
      "την",
      "ΜΕΘ"
    ],
    "tags": [
      "O",
      "O",
      "B-TYPE",
      "B-SIZE",
      "O",
      "O",
      "B-ZONE"
    ],
    "intent": "FETCH"
  },
  {
    "tokens": [
      "Άνοιξε",
      "το",
      "κουτί",
      "στη",
      "Φαρμακείο"
    ],
    "tags": [
      "O",
      "O",
      "B-TYPE",
      "O",
      "B-ZONE"
    ],
    "intent": "OPEN"
  },
  {
    "tokens": [
      "Φέρε",
      "το",
      "μικρό"
    ],
    "tags": [
      "O",
      "O",
      "B-SIZE"
    ],
    "intent": "FETCH"
  },
  {
    "tokens": [
      "Άνοιξε",
      "το"
    ],
    "tags": [
      "O",
      "O"
    ],
    "intent": "OPEN"
  },
  {
    "tokens": [
      "Κλείσε",
      "το",
      "κουτί"
    ],
    "tags": [
      "O",
      "O",
      "B-TYPE"
    ],
    "intent": "CLOSE"
  },
  {
    "tokens": [
      "Φέρε",
      "μου",
      "τη",
      "επίδεσμος",
      "5x5",
      "από",
      "την",
      "Αποθήκη"
    ],
    "tags": [
      "O",
      "O",
      "O",
      "B-TYPE",
      "B-SIZE",
      "O",
      "O",
      "B-ZONE"
    ],
    "intent": "FETCH"
  },
  {
    "tokens": [
      "Φέρτε",
      "τη",
      "γάζες",
      "5x5",
      "από",
      "την",
      "Αποθήκη"
    ],
    "tags": [
      "O",
      "O",
      "B-TYPE",
      "B-SIZE",
      "O",
      "O",
      "B-ZONE"
    ],
    "intent": "FETCH"
  },
  {
    "tokens": [
      "Δες",
      "το",
      "γάζες"
    ],
    "tags": [
      "O",
      "O",
      "B-TYPE"
    ],
    "intent": "INSPECT"
  },
  {
    "tokens": [
      "Φέρε",
      "τη",
      "γάζες",
      "μεσαία",
      "από",
      "την",
      "Αποθήκη"
    ],
    "tags": [
      "O",
      "O",
      "B-TYPE",
      "B-SIZE",
      "O",
      "O",
      "B-ZONE"
    ],
    "intent": "FETCH"
  },
  {
    "tokens": [
      "Βάλε",
      "το",
      "θερμόμετρο",
      "ληγμένο"
    ],
    "tags": [
      "O",
      "O",
      "B-TYPE",
      "B-STATE"
    ],
    "intent": "PLACE"
  },
  {
    "tokens": [
      "Φέρε",
      "το",
      "μικρό"
    ],
    "tags": [
      "O",
      "O",
      "B-SIZE"
    ],
    "intent": "FETCH"
  },
  {
    "tokens": [
      "Χορήγησε",
      "το",
      "αντιβιοτικό"
    ],
    "tags": [
      "O",
      "O",
      "B-TYPE"
    ],
    "intent": "GIVE"
  },
  {
    "tokens": [
      "Πάρε",
      "τη",
      "ιβουπροφένη",
      "μεσαίο",
      "από",
      "την",
      "Αποθήκη"
    ],
    "tags": [
      "O",
      "O",
      "B-TYPE",
      "B-SIZE",
      "O",
      "O",
      "B-ZONE"
    ],
    "intent": "FETCH"
  },
  {
    "tokens": [
      "Δώσε",
      "το",
      "αντιβιοτικό"
    ],
    "tags": [
      "O",
      "O",
      "B-TYPE"
    ],
    "intent": "GIVE"
  },
  {
    "tokens": [
      "Φέρε",
      "τη",
      "παρακεταμόλη",
      "18g",
      "από",
      "την",
      "Φαρμακείο"
    ],
    "tags": [
      "O",
      "O",
      "B-TYPE",
      "B-SIZE",
      "O",
      "O",
      "B-ZONE"
    ],
    "intent": "FETCH"
  },
  {
    "tokens": [
      "Τσέκαρε",
      "το",
      "γάζες"
    ],
    "tags": [
      "O",
      "O",
      "B-TYPE"
    ],
    "intent": "INSPECT"
  },
  {
    "tokens": [
      "Σύριγγα",
      "1ml"
    ],
    "tags": [
      "B-TYPE",
      "B-SIZE"
    ],
    "intent": "FETCH"
  },
  {
    "tokens": [
      "Δες",
      "το",
      "σύριγγα"
    ],
    "tags": [
      "O",
      "O",
      "B-TYPE"
    ],
    "intent": "INSPECT"
  },
  {
    "tokens": [
      "Άφησε",
      "το",
      "σύριγγα",
      "ληγμένο"
    ],
    "tags": [
      "O",
      "O",
      "B-TYPE",
      "B-STATE"
    ],
    "intent": "PLACE"
  },
  {
    "tokens": [
      "Κλείσε",
      "το",
      "κουτί"
    ],
    "tags": [
      "O",
      "O",
      "B-TYPE"
    ],
    "intent": "CLOSE"
  },
  {
    "tokens": [
      "Βάλε",
      "το",
      "αντιβιοτικό",
      "ληγμένη"
    ],
    "tags": [
      "O",
      "O",
      "B-TYPE",
      "B-STATE"
    ],
    "intent": "PLACE"
  },
  {
    "tokens": [
      "Αποθήκη",
      "γάζες"
    ],
    "tags": [
      "B-ZONE",
      "B-TYPE"
    ],
    "intent": "FETCH"
  },
  {
    "tokens": [
      "Κλείστο"
    ],
    "tags": [
      "O"
    ],
    "intent": "CLOSE"
  },
  {
    "tokens": [
      "Κλείσε",
      "το",
      "κουτί"
    ],
    "tags": [
      "O",
      "O",
      "B-TYPE"
    ],
    "intent": "CLOSE"
  },
  {
    "tokens": [
      "Άφησε",
      "το",
      "επίδεσμο",
      "ληγμένη"
    ],
    "tags": [
      "O",
      "O",
      "B-TYPE",
      "B-STATE"
    ],
    "intent": "PLACE"
  },
  {
    "tokens": [
      "Φέρτε",
      "τη",
      "ιβουπροφένη",
      "μεγάλη",
      "από",
      "την",
      "Φαρμακείο"
    ],
    "tags": [
      "O",
      "O",
      "B-TYPE",
      "B-SIZE",
      "O",
      "O",
      "B-ZONE"
    ],
    "intent": "FETCH"
  },
  {
    "tokens": [
      "Ξεκλείδωσε",
      "το",
      "κουτί",
      "στη",
      "Αποθήκη"
    ],
    "tags": [
      "O",
      "O",
      "B-TYPE",
      "O",
      "B-ZONE"
    ],
    "intent": "OPEN"
  },
  {
    "tokens": [
      "Φέρτε",
      "τη",
      "κουτί",
      "10x10",
      "από",
      "την",
      "Αποθήκη"
    ],
    "tags": [
      "O",
      "O",
      "B-TYPE",
      "B-SIZE",
      "O",
      "O",
      "B-ZONE"
    ],
    "intent": "FETCH"
  },
  {
    "tokens": [
      "Τοποθέτησε",
      "το",
      "βελόνα",
      "ανοιχτό"
    ],
    "tags": [
      "O",
      "O",
      "B-TYPE",
      "B-STATE"
    ],
    "intent": "PLACE"
  },
  {
    "tokens": [
      "Κλείστο"
    ],
    "tags": [
      "O"
    ],
    "intent": "CLOSE"
  },
  {
    "tokens": [
      "Τοποθέτησε",
      "το",
      "οξύμετρο",
      "ληγμένο"
    ],
    "tags": [
      "O",
      "O",
      "B-TYPE",
      "B-STATE"
    ],
    "intent": "PLACE"
  },
  {
    "tokens": [
      "Φέρε",
      "τη",
      "οξύμετρο",
      "μεγάλο",
      "από",
      "την",
      "Φαρμακείο"
    ],
    "tags": [
      "O",
      "O",
      "B-TYPE",
      "B-SIZE",
      "O",
      "O",
      "B-ZONE"
    ],
    "intent": "FETCH"
  },
  {
    "tokens": [
      "Δώσε",
      "εκείνο"
    ],
    "tags": [
      "O",
      "O"
    ],
    "intent": "GIVE"
  },
  {
    "tokens": [
      "Έλεγξε",
      "το",
      "σφυγμόμετρο"
    ],
    "tags": [
      "O",
      "O",
      "B-TYPE"
    ],
    "intent": "INSPECT"
  },
  {
    "tokens": [
      "Κλείσε",
      "το",
      "κουτί"
    ],
    "tags": [
      "O",
      "O",
      "B-TYPE"
    ],
    "intent": "CLOSE"
  },
  {
    "tokens": [
      "Βελόνα",
      "21g"
    ],
    "tags": [
      "B-TYPE",
      "B-SIZE"
    ],
    "intent": "FETCH"
  },
  {
    "tokens": [
      "Κλείστο"
    ],
    "tags": [
      "O"
    ],
    "intent": "CLOSE"
  },
  {
    "tokens": [
      "Άνοιξε",
      "το",
      "κουτί",
      "στη",
      "Φαρμακείο"
    ],
    "tags": [
      "O",
      "O",
      "B-TYPE",
      "O",
      "B-ZONE"
    ],
    "intent": "OPEN"
  },
  {
    "tokens": [
      "Τοποθέτησε",
      "το",
      "επίδεσμο",
      "ληγμένο"
    ],
    "tags": [
      "O",
      "O",
      "B-TYPE",
      "B-STATE"
    ],
    "intent": "PLACE"
  },
  {
    "tokens": [
      "Τη",
      "μεγάλη",
      "γάζα"
    ],
    "tags": [
      "O",
      "B-SIZE",
      "B-TYPE"
    ],
    "intent": "FETCH"
  },
  {
    "tokens": [
      "Φέρε",
      "μου",
      "τη",
      "γάζες",
      "μικρό",
      "από",
      "την",
      "Φαρμακείο"
    ],
    "tags": [
      "O",
      "O",
      "O",
      "B-TYPE",
      "B-SIZE",
      "O",
      "O",
      "B-ZONE"
    ],
    "intent": "FETCH"
  },
  {
    "tokens": [
      "Κλείστο"
    ],
    "tags": [
      "O"
    ],
    "intent": "CLOSE"
  },
  {
    "tokens": [
      "Ξεκλείδωσε",
      "το",
      "κουτί",
      "στη",
      "Θάλαμος"
    ],
    "tags": [
      "O",
      "O",
      "B-TYPE",
      "O",
      "B-ZONE"
    ],
    "intent": "OPEN"
  },
  {
    "tokens": [
      "Δώσε",
      "εκείνο"
    ],
    "tags": [
      "O",
      "O"
    ],
    "intent": "GIVE"
  },
  {
    "tokens": [
      "Παρέδωσε",
      "τη",
      "κουτί",
      "5ml",
      "από",
      "την",
      "Θάλαμος"
    ],
    "tags": [
      "O",
      "O",
      "B-TYPE",
      "B-SIZE",
      "O",
      "O",
      "B-ZONE"
    ],
    "intent": "FETCH"
  },
  {
    "tokens": [
      "Βάλε",
      "το",
      "βελόνα",
      "ανοιχτό"
    ],
    "tags": [
      "O",
      "O",
      "B-TYPE",
      "B-STATE"
    ],
    "intent": "PLACE"
  },
  {
    "tokens": [
      "Τη",
      "μεγάλη",
      "γάζα"
    ],
    "tags": [
      "O",
      "B-SIZE",
      "B-TYPE"
    ],
    "intent": "FETCH"
  },
  {
    "tokens": [
      "Πάρε",
      "τη",
      "αντιβιοτικό",
      "5ml",
      "από",
      "την",
      "ΜΕΘ"
    ],
    "tags": [
      "O",
      "O",
      "B-TYPE",
      "B-SIZE",
      "O",
      "O",
      "B-ZONE"
    ],
    "intent": "FETCH"
  },
  {
    "tokens": [
      "Άνοιξε",
      "το"
    ],
    "tags": [
      "O",
      "O"
    ],
    "intent": "OPEN"
  },
  {
    "tokens": [
      "Ληγμένο",
      "είναι;"
    ],
    "tags": [
      "B-STATE",
      "O"
    ],
    "intent": "INSPECT"
  },
  {
    "tokens": [
      "Τοποθέτησε",
      "το",
      "οξύμετρο",
      "αποστειρωμένη"
    ],
    "tags": [
      "O",
      "O",
      "B-TYPE",
      "B-STATE"
    ],
    "intent": "PLACE"
  },
  {
    "tokens": [
      "Φέρε",
      "τη",
      "θερμόμετρο",
      "μικρό",
      "από",
      "την",
      "ΜΕΘ"
    ],
    "tags": [
      "O",
      "O",
      "B-TYPE",
      "B-SIZE",
      "O",
      "O",
      "B-ZONE"
    ],
    "intent": "FETCH"
  },
  {
    "tokens": [
      "Δώσε",
      "το",
      "γάζα"
    ],
    "tags": [
      "O",
      "O",
      "B-TYPE"
    ],
    "intent": "GIVE"
  },
  {
    "tokens": [
      "Πάρε",
      "τη",
      "επίδεσμο",
      "μεγάλη",
      "από",
      "την",
      "ΜΕΘ"
    ],
    "tags": [
      "O",
      "O",
      "B-TYPE",
      "B-SIZE",
      "O",
      "O",
      "B-ZONE"
    ],
    "intent": "FETCH"
  },
  {
    "tokens": [
      "Κλείσε",
      "το",
      "κουτί"
    ],
    "tags": [
      "O",
      "O",
      "B-TYPE"
    ],
    "intent": "CLOSE"
  },
  {
    "tokens": [
      "Βάλε",
      "το",
      "γάζες",
      "ληγμένη"
    ],
    "tags": [
      "O",
      "O",
      "B-TYPE",
      "B-STATE"
    ],
    "intent": "PLACE"
  },
  {
    "tokens": [
      "Βελόνα",
      "21g"
    ],
    "tags": [
      "B-TYPE",
      "B-SIZE"
    ],
    "intent": "FETCH"
  },
  {
    "tokens": [
      "Φέρε",
      "μου",
      "τη",
      "επίδεσμος",
      "μεσαία",
      "από",
      "την",
      "Αποθήκη"
    ],
    "tags": [
      "O",
      "O",
      "O",
      "B-TYPE",
      "B-SIZE",
      "O",
      "O",
      "B-ZONE"
    ],
    "intent": "FETCH"
  },
  {
    "tokens": [
      "Τοποθέτησε",
      "το",
      "βελόνα",
      "ανοιχτό"
    ],
    "tags": [
      "O",
      "O",
      "B-TYPE",
      "B-STATE"
    ],
    "intent": "PLACE"
  },
  {
    "tokens": [
      "Άνοιξε",
      "το"
    ],
    "tags": [
      "O",
      "O"
    ],
    "intent": "OPEN"
  },
  {
    "tokens": [
      "Άνοιξε",
      "το",
      "κουτί",
      "στη",
      "ΜΕΘ"
    ],
    "tags": [
      "O",
      "O",
      "B-TYPE",
      "O",
      "B-ZONE"
    ],
    "intent": "OPEN"
  },
  {
    "tokens": [
      "Κλείστο"
    ],
    "tags": [
      "O"
    ],
    "intent": "CLOSE"
  },
  {
    "tokens": [
      "Κλείσε",
      "το",
      "κουτί"
    ],
    "tags": [
      "O",
      "O",
      "B-TYPE"
    ],
    "intent": "CLOSE"
  },
  {
    "tokens": [
      "Έλεγξε",
      "τα",
      "ληγμένα"
    ],
    "tags": [
      "O",
      "O",
      "B-STATE"
    ],
    "intent": "INSPECT"
  },
  {
    "tokens": [
      "Δώσε",
      "εκείνο"
    ],
    "tags": [
      "O",
      "O"
    ],
    "intent": "GIVE"
  },
  {
    "tokens": [
      "Φέρτε",
      "τη",
      "κουτί",
      "5x5",
      "από",
      "την",
      "Θάλαμος"
    ],
    "tags": [
      "O",
      "O",
      "B-TYPE",
      "B-SIZE",
      "O",
      "O",
      "B-ZONE"
    ],
    "intent": "FETCH"
  },
  {
    "tokens": [
      "Φέρτε",
      "τη",
      "γάζα",
      "μεγάλη",
      "από",
      "την",
      "Φαρμακείο"
    ],
    "tags": [
      "O",
      "O",
      "B-TYPE",
      "B-SIZE",
      "O",
      "O",
      "B-ZONE"
    ],
    "intent": "FETCH"
  },
  {
    "tokens": [
      "Τη",
      "μεγάλη",
      "γάζα"
    ],
    "tags": [
      "O",
      "B-SIZE",
      "B-TYPE"
    ],
    "intent": "FETCH"
  },
  {
    "tokens": [
      "Άφησε",
      "το",
      "γάζα",
      "ανοιχτή"
    ],
    "tags": [
      "O",
      "O",
      "B-TYPE",
      "B-STATE"
    ],
    "intent": "PLACE"
  },
  {
    "tokens": [
      "Κλείστο"
    ],
    "tags": [
      "O"
    ],
    "intent": "CLOSE"
  },
  {
    "tokens": [
      "Ξεκλείδωσε",
      "το",
      "κουτί",
      "στη",
      "Φαρμακείο"
    ],
    "tags": [
      "O",
      "O",
      "B-TYPE",
      "O",
      "B-ZONE"
    ],
    "intent": "OPEN"
  },
  {
    "tokens": [
      "Χορήγησε",
      "το",
      "γάζα"
    ],
    "tags": [
      "O",
      "O",
      "B-TYPE"
    ],
    "intent": "GIVE"
  },
  {
    "tokens": [
      "Χορήγησε",
      "το",
      "παρακεταμόλη"
    ],
    "tags": [
      "O",
      "O",
      "B-TYPE"
    ],
    "intent": "GIVE"
  },
  {
    "tokens": [
      "Έλεγξε",
      "τα",
      "ληγμένα"
    ],
    "tags": [
      "O",
      "O",
      "B-STATE"
    ],
    "intent": "INSPECT"
  },
  {
    "tokens": [
      "Χορήγησε",
      "το",
      "αντιβιοτικό"
    ],
    "tags": [
      "O",
      "O",
      "B-TYPE"
    ],
    "intent": "GIVE"
  },
  {
    "tokens": [
      "Κλείσε",
      "το",
      "κουτί"
    ],
    "tags": [
      "O",
      "O",
      "B-TYPE"
    ],
    "intent": "CLOSE"
  },
  {
    "tokens": [
      "Ξεκλείδωσε",
      "το",
      "κουτί",
      "στη",
      "Φαρμακείο"
    ],
    "tags": [
      "O",
      "O",
      "B-TYPE",
      "O",
      "B-ZONE"
    ],
    "intent": "OPEN"
  },
  {
    "tokens": [
      "Βάλε",
      "το",
      "γάζες",
      "ανοιχτό"
    ],
    "tags": [
      "O",
      "O",
      "B-TYPE",
      "B-STATE"
    ],
    "intent": "PLACE"
  },
  {
    "tokens": [
      "Έλεγξε",
      "το",
      "ιβουπροφένη"
    ],
    "tags": [
      "O",
      "O",
      "B-TYPE"
    ],
    "intent": "INSPECT"
  },
  {
    "tokens": [
      "Βάλε",
      "αυτό",
      "εδώ"
    ],
    "tags": [
      "O",
      "O",
      "O"
    ],
    "intent": "PLACE"
  },
  {
    "tokens": [
      "Βάλε",
      "αυτό",
      "εδώ"
    ],
    "tags": [
      "O",
      "O",
      "O"
    ],
    "intent": "PLACE"
  },
  {
    "tokens": [
      "Φέρε",
      "τη",
      "οξύμετρο",
      "μεσαία",
      "από",
      "την",
      "Αποθήκη"
    ],
    "tags": [
      "O",
      "O",
      "B-TYPE",
      "B-SIZE",
      "O",
      "O",
      "B-ZONE"
    ],
    "intent": "FETCH"
  },
  {
    "tokens": [
      "Φέρε",
      "το",
      "μικρό"
    ],
    "tags": [
      "O",
      "O",
      "B-SIZE"
    ],
    "intent": "FETCH"
  },
  {
    "tokens": [
      "Πάρε",
      "τη",
      "παρακεταμόλη",
      "10x10",
      "από",
      "την",
      "Αποθήκη"
    ],
    "tags": [
      "O",
      "O",
      "B-TYPE",
      "B-SIZE",
      "O",
      "O",
      "B-ZONE"
    ],
    "intent": "FETCH"
  },
  {
    "tokens": [
      "Κλείσε",
      "το",
      "κουτί"
    ],
    "tags": [
      "O",
      "O",
      "B-TYPE"
    ],
    "intent": "CLOSE"
  },
  {
    "tokens": [
      "Εξέτασε",
      "το",
      "αντιβιοτικό"
    ],
    "tags": [
      "O",
      "O",
      "B-TYPE"
    ],
    "intent": "INSPECT"
  },
  {
    "tokens": [
      "Σύριγγα",
      "1ml"
    ],
    "tags": [
      "B-TYPE",
      "B-SIZE"
    ],
    "intent": "FETCH"
  },
  {
    "tokens": [
      "Σύριγγα",
      "1ml"
    ],
    "tags": [
      "B-TYPE",
      "B-SIZE"
    ],
    "intent": "FETCH"
  },
  {
    "tokens": [
      "Έλεγξε",
      "τα",
      "ληγμένα"
    ],
    "tags": [
      "O",
      "O",
      "B-STATE"
    ],
    "intent": "INSPECT"
  },
  {
    "tokens": [
      "Δώσε",
      "το",
      "μεγάλο"
    ],
    "tags": [
      "O",
      "O",
      "B-SIZE"
    ],
    "intent": "GIVE"
  },
  {
    "tokens": [
      "Κλείσε",
      "το",
      "κουτί"
    ],
    "tags": [
      "O",
      "O",
      "B-TYPE"
    ],
    "intent": "CLOSE"
  },
  {
    "tokens": [
      "Κλείσε",
      "το",
      "κουτί"
    ],
    "tags": [
      "O",
      "O",
      "B-TYPE"
    ],
    "intent": "CLOSE"
  },
  {
    "tokens": [
      "Χορήγησε",
      "το",
      "γάζα"
    ],
    "tags": [
      "O",
      "O",
      "B-TYPE"
    ],
    "intent": "GIVE"
  },
  {
    "tokens": [
      "Άφησε",
      "το",
      "παρακεταμόλη",
      "ανοιχτή"
    ],
    "tags": [
      "O",
      "O",
      "B-TYPE",
      "B-STATE"
    ],
    "intent": "PLACE"
  },
  {
    "tokens": [
      "Βάλε",
      "αυτό",
      "εδώ"
    ],
    "tags": [
      "O",
      "O",
      "O"
    ],
    "intent": "PLACE"
  },
  {
    "tokens": [
      "Δώσε",
      "εκείνο"
    ],
    "tags": [
      "O",
      "O"
    ],
    "intent": "GIVE"
  },
  {
    "tokens": [
      "Βάλε",
      "το",
      "επίδεσμος",
      "αποστειρωμένο"
    ],
    "tags": [
      "O",
      "O",
      "B-TYPE",
      "B-STATE"
    ],
    "intent": "PLACE"
  },
  {
    "tokens": [
      "Φέρε",
      "μου",
      "τη",
      "γάζες",
      "10x10",
      "από",
      "την",
      "ΜΕΘ"
    ],
    "tags": [
      "O",
      "O",
      "O",
      "B-TYPE",
      "B-SIZE",
      "O",
      "O",
      "B-ZONE"
    ],
    "intent": "FETCH"
  },
  {
    "tokens": [
      "Τοποθέτησε",
      "το",
      "θερμόμετρο",
      "αποστειρωμένη"
    ],
    "tags": [
      "O",
      "O",
      "B-TYPE",
      "B-STATE"
    ],
    "intent": "PLACE"
  },
  {
    "tokens": [
      "Ξεκλείδωσε",
      "το",
      "κουτί",
      "στη",
      "ΜΕΘ"
    ],
    "tags": [
      "O",
      "O",
      "B-TYPE",
      "O",
      "B-ZONE"
    ],
    "intent": "OPEN"
  },
  {
    "tokens": [
      "Άφησε",
      "το",
      "κουτί",
      "ανοιχτή"
    ],
    "tags": [
      "O",
      "O",
      "B-TYPE",
      "B-STATE"
    ],
    "intent": "PLACE"
  },
  {
    "tokens": [
      "Βάλε",
      "το",
      "σφυγμόμετρο",
      "αποστειρωμένη"
    ],
    "tags": [
      "O",
      "O",
      "B-TYPE",
      "B-STATE"
    ],
    "intent": "PLACE"
  },
  {
    "tokens": [
      "Τη",
      "μεγάλη",
      "γάζα"
    ],
    "tags": [
      "O",
      "B-SIZE",
      "B-TYPE"
    ],
    "intent": "FETCH"
  },
  {
    "tokens": [
      "Κλείστο"
    ],
    "tags": [
      "O"
    ],
    "intent": "CLOSE"
  },
  {
    "tokens": [
      "Δες",
      "το",
      "γάζες"
    ],
    "tags": [
      "O",
      "O",
      "B-TYPE"
    ],
    "intent": "INSPECT"
  },
  {
    "tokens": [
      "Παρακεταμόλη",
      "ΜΕΘ"
    ],
    "tags": [
      "B-TYPE",
      "B-ZONE"
    ],
    "intent": "FETCH"
  }
]